Workbook
Name _1_USD: #REF!
Name _1_USD: #REF!
Name _1_USD: #REF!
Name _1_USD: #REF!
Name _1_USD: #REF!
Name _1_USD: #REF!
Name _1_USD: #REF!
Name _1_USD: #REF!
Name _1_USD: #REF!
Name _1_USD: #REF!
Name _1_USD: #REF!
Name _1_USD: #REF!
Name _1_USD: #REF!
Name _1_USD: #REF!
Name _1_USD: #REF!
Name _1_USD: #REF!
Name _1_USD: #REF!
Name _1_USD: #REF!
Name _1_USD: #REF!
Name _1_USD: #REF!
Name _1_USD: #REF!
Name _1_USD: #REF!
Name _1_USD: #REF!
Name _1_USD: #REF!
Name _1_USD: #REF!
Name _1_USD: #REF!
Name _1_USD: #REF!
Name _1_USD: #REF!
Name _1_USD: #REF!
Name _1_USD: #REF!
Name _1_USD: #REF!
Name _1_USD: #REF!
Name _1_USD: #REF!
Name _1_USD: #REF!
Name _1_USD: #REF!
Name _1_USD: #REF!
Name _1_USD: #REF!
Name _1_USD: #REF!
Name _1_USD: #REF!
Name _1_USD: #REF!
Name _2_: #REF!
Name _2_: #REF!
Name _2_: #REF!
Name _2_: #REF!
Name _2_: #REF!
Name _2_: #REF!
Name _2_: #REF!
Name _2_: #REF!
Name _2_: #REF!
Name _2_: #REF!
Name _2_: #REF!
Name _2_: #REF!
Name _2_: #REF!
Name _2_: #REF!
Name _2_: #REF!
Name _2_: #REF!
Name _2_: #REF!
Name _2_: #REF!
Name _2_: #REF!
Name _2_: #REF!

Sheet титульный лист
A1: Государственная корпорация «Роскосмос»
A3: Сокращенное название организации | H3: Утверждаю
H4: Генеральный директор
H6: _________________ / _______________
H7: " _____" _______________ 2017 г.
A9: Производственно-технологический П А С П О Р Т
A10: организации государственной корпорации «Роскосмос»
A14: ________________________________________________________________________________
A15: (полное наименование и расположение организации)
G18: Главный инженер | H18: _________________/ _______________
H19: (подпись) (Ф.И.О.)
G20: Заместитель генерального директора по экономике и финансам | H20: _________________/ _______________
H21: (подпись) (Ф.И.О.)
G22: Заместитель генерального директора по персоналу | H22: _________________/ _______________
H23: (подпись) (Ф.И.О.)
G24: Главный технолог | H24: _________________/ _______________
H25: (подпись) (Ф.И.О.)
G26: Главный механик | H26: _________________/ _______________
H27: (подпись) (Ф.И.О.)

Sheet Перечень
A1: Перечень таблиц формы паспорта организации
A3: Раздел формы паспорта | B3: № таблицы | C3: Название таблицы формы паспорта
A4: 1 | B4: 2 | C4: 3
A5: ='раздел I'!A9:N9 -> I. ОБЩАЯ ХАРАКТЕРИСТИКА ОРГАНИЗАЦИИ | B5: б/н | C5: =Пояснит.записка!A4 -> Пояснительная записка
B6: =RIGHT('А-1'!C1,LEN('А-1'!C1)-8) -> А/1 | C6: ='А-1'!A4 -> Адресно-справочная информация об организации
B7: =RIGHT('А-2'!I1,LEN('А-2'!I1)-8) -> А/2 | C7: ='А-2'!A4 -> Сведения о филиалах и обособленных производственных подразделениях
B8: =RIGHT('А-3'!D1,LEN('А-3'!D1)-8) -> А/3 | C8: ='А-3'!A4 -> Ситуационный план организации
B9: =RIGHT('А-4'!D1,LEN('А-4'!D1)-8) -> А/4 | C9: ='А-4'!A4 -> Схема генерального плана (М 1 : 5000)
B10: =RIGHT('А-5'!D1,LEN('А-5'!D1)-8) -> А/5 | C10: ='А-5'!A4 -> Организационно-структурная схема (схема управления организацией)
B11: =RIGHT('А-6'!L1,LEN('А-6'!L1)-8) -> А/6 | C11: ='А-6'!A4 -> Сведения о дочерних, в т.ч. малых предпринимательских структурах
B12: =RIGHT('А-7'!K1,LEN('А-7'!K1)-8) -> А/7 | C12: ='А-7'!A4 -> Сведения о ценных бумагах акционерного общества и ценных бумагах его дочерних (зависимых) обществ
B13: =RIGHT('I-1'!F1,LEN('I-1'!F1)-8) -> I/1 | C13: ='I-1'!A4 -> Сведения о лицензиях на виды деятельности
B14: =RIGHT('I-2'!N1,LEN('I-2'!N1)-8) -> I/2 | C14: ='I-2'!A4 -> Сведения о сертификатах соответствия (заключениях)
B15: =RIGHT('I-3'!C1,LEN('I-3'!C1)-8) -> I/3 | C15: ='I-3'!A4 -> Информация об официальном аудиторе организации
B16: =RIGHT('I-4'!K1,LEN('I-4'!K1)-8) -> I/4 | C16: ='I-4'!A4 -> Сведения об имущественных правах акционеров (участников) организации (холдинга)
B17: =RIGHT('I-5'!L1,LEN('I-5'!L1)-8) -> I/5 | C17: ='I-5'!A4 -> Сведения об участии в других организациях
B18: =RIGHT('I-6'!D1,LEN('I-6'!D1)-8) -> I/6 | C18: ='I-6'!A4 -> Сведения о совете директоров общества
A19: ='раздел II'!A9:O9 -> II. ВЫПОЛНЕНИЕ СЕРИЙНЫХ ПОСТАВОК ПРОДУКЦИИ | B19: =RIGHT('II-1'!K1,LEN('II-1'!K1)-8) -> II/1 | C19: ='II-1'!B4 -> Отчет о ходе выполнения и финансирования поставок продукции военного и специального назначения (работ, услуг) по государственному оборонному заказу
B20: =RIGHT('II-2'!I1,LEN('II-2'!I1)-8) -> II/2 | C20: ='II-2'!A4 -> Выпускаемая продукция, основные технические переделы и «узкие места»
B21: =RIGHT('II-3'!J1,LEN('II-3'!J1)-8) -> II/3 | C21: ='II-3'!A4 -> «Узкие места» производственного процесса изделий РКТ в организации (на плановый период)
B22: =RIGHT('II-4'!I1,LEN('II-4'!I1)-8) -> II/4 | C22: ='II-4'!A4 -> Кооперационные связи организации
A23: ='раздел III'!A9:O9 -> III. ВЫПОЛНЕНИЕ НИОКР ПО СПЕЦПРОДУКЦИИ | B23: =RIGHT('III-1'!K1,LEN('III-1'!K1)-8) -> III/1 | C23: ='III-1'!B4 -> Сведения об участии в реализации государственных и федеральных целевых программ
B24: =RIGHT('III-2'!J1,LEN('III-2'!J1)-8) -> III/2 | C24: ='III-2'!B4 -> Отчет о ходе выполнения и финансирования работ НИОКР по спецпродукции
B25: =RIGHT('III-3'!J1,LEN('III-3'!J1)-8) -> III/3 | C25: ='III-3'!B4 -> Планируемые НИОКР по спецпродукции
A26: ='раздел IV'!A9 -> IV. ВЫПОЛНЕНИЕ РАБОТ ПО ПРОДУКЦИИ ГРАЖДАНСКОГО НАЗНАЧЕНИЯ | B26: =RIGHT('IV-1'!O1,LEN('IV-1'!O1)-8) -> IV/1 | C26: ='IV-1'!A4 -> Производство продукции гражданского назначения, товаров народного потребления и услуг, оказанных организацией
B27: =RIGHT('IV-2'!C1,LEN('IV-2'!C1)-8) -> IV/2 | C27: ='IV-2'!A5 -> Ожидаемое развитие, виды технологий и проблемы реализации программы товаров народного потребления. Выделенные производственные площади и оборудование
B28: =RIGHT('IV-3'!G1,LEN('IV-3'!G1)-8) -> IV/3 | C28: ='IV-3'!B4 -> Инновационные проекты по продукции гражданского и двойного назначения
A29: ='раздел V'!A9 -> V. ВЫПОЛНЕНИЕ РАБОТ ПО ГОСУДАРСТВЕННЫМ КОНТРАКТАМ | B29: =RIGHT('V-1'!L1,LEN('V-1'!L1)-8) -> V/1 | C29: ='V-1'!A4 -> Продукция отечественных производителей, закупаемая в обеспечение выполнения государственных контрактов (контрактов)
B30: =RIGHT('V-2'!L1,LEN('V-2'!L1)-8) -> V/2 | C30: ='V-2'!A4 -> Продукция, импортируемая в обеспечение выполнения государственных контрактов (контрактов)
B31: =RIGHT('V-3'!J1,LEN('V-3'!J1)-8) -> V/3 | C31: ='V-3'!A4 -> Сведения о продукции (материалах и комплектующих), используемой при выполнении государственных контрактов (контрактов), производство которой прекращено (приостановлено) или находится за пределами Российской Федерации и импорт которой ограничен
A32: ='раздел VI'!B9 -> VI. ПРОИЗВОДСТВЕННО-ТЕХНОЛОГИЧЕСКАЯ БАЗА | B32: =RIGHT('VI-1'!K1,LEN('VI-1'!K1)-8) -> VI/1 | C32: ='VI-1'!B4 -> Производственные основные фонды - возрастной состав оборудования
B33: =RIGHT('VI-2'!I1,LEN('VI-2'!I1)-8) -> VI/2 | C33: ='VI-2'!B4 -> Кодифицированный перечень подразделений по видам производства
B34: =RIGHT('VI-3'!J1,LEN('VI-3'!J1)-8) -> VI/3 | C34: ='VI-3'!B4 -> Состав оборудования организации по видам производств
B35: =RIGHT('VI-4'!K1,LEN('VI-4'!K1)-8) -> VI/4 | C35: ='VI-4'!C5 -> Трудоемкость годовой программы товарного выпуска продукции по видам производств
B36: =RIGHT('VI-5'!M1,LEN('VI-5'!M1)-8) -> VI/5 | C36: ='VI-5'!B3 -> Сведения о приобретенном оборудовании в отчетном году
B37: =RIGHT('VI-6'!H1,LEN('VI-6'!H1)-8) -> I/6 | C37: ='VI-6'!B4 -> Сведения об оборудовании, запланированном к закупке
B38: =RIGHT('VI-7'!N1,LEN('VI-7'!N1)-8) -> #VALUE! | C38: ='VI-7'!B3 -> Данные по инвестиционным проектам
B39: =RIGHT('VI-8'!K1,LEN('VI-8'!K1)-8) -> VI/8 | C39: ='VI-8'!A4 -> Сведения об арендованном (лизинговом) и полученном на ответственное хранение оборудовании за отчетный год
B40: =RIGHT('VI-9'!I1,LEN('VI-9'!I1)-8) -> VI/9 | C40: ='VI-9'!B4 -> Сведения об оборудовании, переданном в залог или обременённом иным образом (за исключением оборудования, сданного в аренду) в отчетном году
B41: =RIGHT('VI-10'!I1,LEN('VI-10'!I1)-8) -> VI/10 | C41: ='VI-10'!A4 -> Сведения об оборудовании организации, сданном в аренду в отчетном году
B42: =RIGHT('VI-11'!M1,LEN('VI-11'!M1)-8) -> VI/11 | C42: ='VI-11'!A4 -> Сведения об оборудовании, реализованном и списанном (утилизированном) в отчетном году и планируемом к реализации и списанию (утилизации)
B43: =RIGHT('VI-12'!N1,LEN('VI-12'!N1)-8) -> VI/12 | C43: ='VI-12'!B3 -> Наличие испытательных площадок (полигонов)
B44: =RIGHT('VI-13'!G1,LEN('VI-13'!G1)-8) -> VI/13 | C44: ='VI-13'!A4 -> Сводные сведения о стендово-испытательной базе
A45: ='раздел VII'!A9 -> VII. ФИНАНСОВО-ЭКОНОМИЧЕСКАЯ ДЕЯТЕЛЬНОСТЬ | B45: =RIGHT('VII-1'!D1,LEN('VII-1'!D1)-8) -> VII/1 | C45: ='VII-1'!A4 -> Бюджет доходов и расходов за отчетный год
B46: =RIGHT('VII-2'!D1,LEN('VII-2'!D1)-8) -> VII/2 | C46: ='VII-2'!A5 -> Бюджет движения денежных средств
B47: =RIGHT('VII-3'!Q1,LEN('VII-3'!Q1)-8) -> VII/3 | C47: ='VII-3'!A4 -> Сведения о начисленных и уплаченных налогах, сборах и страховых взносах
B48: =RIGHT('VII-4'!J1,LEN('VII-4'!J1)-8) -> VII/4 | C48: ='VII-4'!A5 -> Информация о долгосрочных финансовых вложениях в другие организации
B49: =RIGHT('VII-5'!H1,LEN('VII-5'!H1)-8) -> VII/5 | C49: ='VII-5'!A4 -> Сведения о дебиторской задолженности
B50: =RIGHT('VII-6'!G1,LEN('VII-6'!G1)-8) -> VII/6 | C50: ='VII-6'!A4 -> Сведения о кредиторской задолженности
B51: =RIGHT('VII-7'!H1,LEN('VII-7'!H1)-8) -> VII/7 | C51: ='VII-7'!A4 -> Сведения о субсидиях и бюджетных средствах
B52: =RIGHT('VII-8'!E1,LEN('VII-8'!E1)-8) -> VII/8 | C52: ='VII-8'!A4 -> Амортизация основных фондов и ее использование в отчетном году
A53: ='Раздел VIII'!B9 -> VIII. ВНЕШНЕЭКОНОМИЧЕСКАЯ ДЕЯТЕЛЬНОСТЬ | B53: =RIGHT('VIII-1'!M1,LEN('VIII-1'!M1)-8) -> VIII/1 | C53: ='VIII-1'!A4 -> Контракты и соглашения по внешне-техническому сотрудничеству с зарубежными странами
B54: =RIGHT('VIII-2'!H1,LEN('VIII-2'!H1)-8) -> VIII/2 | C54: ='VIII-2'!A4 -> Общие объемы экспорта продукции и услуг организции
B55: =RIGHT('VIII-3'!G1,LEN('VIII-3'!G1)-8) -> VIII/3 | C55: ='VIII-3'!A4 -> Продукция гражданского назначения поставляемая на экспорт
B56: =RIGHT('VIII-4'!E1,LEN('VIII-4'!E1)-8) -> VIII/4 | C56: ='VIII-4'!B4 -> Общие объемы импорта продукции
B57: =RIGHT('VIII-5'!G1,LEN('VIII-5'!G1)-8) -> VIII/5 | C57: ='VIII-5'!A4 -> Сведения об импортируемой продукции
A58: ='раздел IX'!B9 -> IX. ОБЪЕКТЫ НЕДВИЖИМОСТИ И ЗЕМЕЛЬНЫЕ УЧАСТКИ | B58: =RIGHT('IX-1'!J1,LEN('IX-1'!J1)-8) -> IX/1 | C58: ='IX-1'!A4 -> Сводные сведения об объектах недвижимости
B59: =RIGHT('IX-2'!N1,LEN('IX-2'!N1)-8) -> IX/2 | C59: ='IX-2'!A4 -> Сведения о земельных участках
B60: =RIGHT('IX-3'!O1,LEN('IX-3'!O1)-8) -> IX/3 | C60: ='IX-3'!A4 -> Общие сведения о зданиях и сооружениях, находящихся на балансе организации
B61: =RIGHT('IX-4'!S1,LEN('IX-4'!S1)-8) -> IХ/4 | C61: ='IX-4'!A4 -> Технические характеристики объектов недвижимости
B62: =RIGHT('IX-5'!I1,LEN('IX-5'!I1)-8) -> IX/5 | C62: ='IX-5'!A4 -> Сведения об объектах социальной сферы, находящихся на балансе организации
B63: =RIGHT('IX-6'!J1,LEN('IX-6'!J1)-8) -> IX/6 | C63: ='IX-6'!A4 -> Сведения об объектах незавершенного строительства
B64: =RIGHT('IX-7'!N1,LEN('IX-7'!N1)-8) -> IX/7 | C64: ='IX-7'!A4 -> Сведения о сдаче в аренду объектов недвижимости в отчетном году
B65: =RIGHT('IX-8'!I1,LEN('IX-8'!I1)-8) -> IX/8 | C65: ='IX-8'!B4 -> Сведения об объектах недвижимости, переданных в залог или обремененных иным образом (за исключением аренды)
B66: =RIGHT('IX-9'!O1,LEN('IX-9'!O1)-8) -> IX/9 | C66: ='IX-9'!B5 -> Сведения об объектах недвижимости, отчужденных в отчетном году и планируемых к отчуждению в следующем за отчетным годом
B67: =RIGHT('IX-10'!M1,LEN('IX-10'!M1)-8) -> IX/10 | C67: ='IX-10'!B5 -> Сведения о снесенных (ликвидированных) объектах недвижимости в отчетном году и планируемых к сносу в следующем за отчетным годом
B68: =RIGHT('IX-11'!L1,LEN('IX-11'!L1)-8) -> IX/11 | C68: ='IX-11'!A4 -> Сведения о поступлении денежных средств от использования объектов недвижимости
A69: ='раздел X'!B9 -> X. ИНТЕЛЛЕКТУАЛЬНАЯ СОБСТВЕННОСТЬ И НЕМАТЕРИАЛЬНЫЕ АКТИВЫ | B69: =RIGHT('X-1'!N1,LEN('X-1'!N1)-8) -> X/1 | C69: ='X-1'!A4 -> Сведения о полученных охранных документах и поданных заявках на объекты интеллектуальной собственности в отчетном году
B70: =RIGHT('Х-2'!L1,LEN('Х-2'!L1)-8) -> X/2 | C70: ='Х-2'!A4 -> Введение объектов интеллектуальной собственности (ОИС) в хозяйственный и гражданско-правовой оборот
B71: =RIGHT('X-3'!H1,LEN('X-3'!H1)-8) -> X/3 | C71: ='X-3'!A4 -> Сведения об использовании введенных в отчетном году ОИС в собственном производстве
B72: =RIGHT('X-4'!I1,LEN('X-4'!I1)-8) -> X/4 | C72: ='X-4'!B4 -> Сведения об учтенных в составе нематериальных активов объектах интеллектуальной собственности по состоянию на конец отчетного года
B73: =RIGHT('X-5'!H1,LEN('X-5'!H1)-8) -> X/5 | C73: ='X-5'!A4 -> Финансовые результаты процессов коммерциализации объектов интеллектуальной собственности и трансфера технологий (внутренний рынок)
B74: =RIGHT('X-6'!H1,LEN('X-6'!H1)-8) -> X/6 | C74: ='X-6'!A4 -> Финансовые результаты процессов коммерциализации объектов интеллектуальной собственности и трансфера технологий (экспорт-импорт)
A75: ='раздел XI'!B9 -> ХI. ПЕРСОНАЛ ОРГАНИЗАЦИИ | B75: =RIGHT('XI-1'!L1,LEN('XI-1'!L1)-8) -> XI/1 | C75: ='XI-1'!A4 -> Структура численности персонала и оплата труда
B76: =RIGHT('XI-2'!J1,LEN('XI-2'!J1)-8) -> XI/2 | C76: ='XI-2'!B4 -> Справка-объективка на руководящий состав организации
B77: =RIGHT('XI-3'!F1,LEN('XI-3'!F1)-8) -> ХI/3 | C77: ='XI-3'!A4 -> Сведения о повышении квалификации и переподготовке руководителей и служащих
B78: =RIGHT('ХI-4'!K1,LEN('ХI-4'!K1)-8) -> ХI/4 | C78: ='ХI-4'!A4 -> Список работников, планируемых для выдвижения на должности генерального директора, его заместителей и главного бухгалтера
B79: =RIGHT('XI-5'!C1,LEN('XI-5'!C1)-8) -> ХI/5 | C79: ='XI-5'!A4 -> Сведения о профессиональном обучении рабочих
B80: =RIGHT('XI-6'!J1,LEN('XI-6'!J1)-8) -> ХI/6 | C80: ='XI-6'!A4 -> Востребованность должностей и специальностей персонала организации в части персонала со средним профессиональным образованием по состоянию на конец отчетного периода
B81: =RIGHT('XI-7'!J1,LEN('XI-7'!J1)-8) -> ХI/7 | C81: ='XI-7'!A4 -> Востребованность должностей и специальностей персонала организации в части специалистов с высшим образованием по состоянию на конец отчетного периода
B82: =RIGHT('XI-8'!E1,LEN('XI-8'!E1)-8) -> XI/8 | C82: ='XI-8'!A4 -> Сведения об условиях труда
B83: =RIGHT('ХI-9'!F1,LEN('ХI-9'!F1)-8) -> ХI/9 | C83: ='ХI-9'!A4 -> Cписок работников организации, имеющих ученую степень кандидата (доктора) наук
A84: ='раздел XII'!B9 -> ХII. СЕРТИФИКАЦИЯ И КАЧЕСТВО | B84: =RIGHT('XII-1'!A1,LEN('XII-1'!A1)-8) -> XII/1 | C84: ='XII-1'!A4 -> Отчет о результатах анализа деятельности организации в области качества
B85: =RIGHT('XII-2'!K1,LEN('XII-2'!K1)-8) -> XII/2 | C85: ='XII-2'!A4 -> Сведения по качеству документации за отчетный год
B86: =RIGHT('XII-3'!M1,LEN('XII-3'!M1)-8) -> XII/3 | C86: ='XII-3'!A4 -> Сведения о собственных затратах на погашение рекламаций за отчетный год
A87: ='раздел XIII'!A9 -> ХIII. УРОВЕНЬ АВТОМАТИЗАЦИИ | B87: =RIGHT('XIII-1'!H1,LEN('XIII-1'!H1)-8) -> XIII/1 | C87: ='XIII-1'!A4 -> Внешние каналы связи
B88: =RIGHT('XIII-2'!I1,LEN('XIII-2'!I1)-8) -> XIII/2 | C88: ='XIII-2'!A4 -> Локально-вычислительная сеть
B89: =RIGHT('XIII-3'!J1,LEN('XIII-3'!J1)-8) -> XIII/3 | C89: ='XIII-3'!A4 -> Серверное оборудование (серверы и хранилища данных)
B90: =RIGHT('XIII-4'!I1,LEN('XIII-4'!I1)-8) -> XIII/4 | C90: ='XIII-4'!A4 -> Персональные компьютеры и терминальные рабочие станции
B91: =RIGHT('XIII-5'!K1,LEN('XIII-5'!K1)-8) -> XIII/5 | C91: ='XIII-5'!A4 -> Периферийное оборудование
B92: =RIGHT('XIII-6'!J1,LEN('XIII-6'!J1)-8) -> XIII/6 | C92: ='XIII-6'!A4 -> Операционные системы, СУБД, АСУ и прикладные программы
B93: =RIGHT('XIII-7'!J1,LEN('XIII-7'!J1)-8) -> XIII/7 | C93: ='XIII-7'!B4 -> Создание и внедрение автоматизированных систем
A94: ='Раздел XIV'!A9 -> XIV. ПОТРЕБЛЕНИЕ РЕСУРСОВ, ЭНЕРГОСБЕРЕЖЕНИЕ И ОХРАНА ОКРУЖАЮЩЕЙ СРЕДЫ | B94: =RIGHT('XIV-1'!F1,LEN('XIV-1'!F1)-8) -> XIV/1 | C94: ='XIV-1'!A4 -> Сведения о расходах (размерах оплаты) ресурсов по видам
B95: =RIGHT('XIV-2'!D1,LEN('XIV-2'!D1)-8) -> XIV/2 | C95: ='XIV-2'!B4 -> Сведения о потреблении электроэнергии на технологические нужды
B96: =RIGHT('XIV-3'!D1,LEN('XIV-3'!D1)-8) -> XIV/3 | C96: ='XIV-3'!A4 -> Водопотребление и водоотведение за отчетный год
B97: =RIGHT('XIV-4'!I1,LEN('XIV-4'!I1)-8) -> XIV/4 | C97: ='XIV-4'!B4 -> Сведения о системе инженерно-технических сетей, коммуникаций и инфраструктуры зданий и сооружений, производственных площадок
B98: =RIGHT('XIV-5'!K1,LEN('XIV-5'!K1)-8) -> XIV/5 | C98: ='XIV-5'!B4 -> Мероприятия по энергосбережению и охране окружающей среды

Sheet раздел I
A9: I. ОБЩАЯ ХАРАКТЕРИСТИКА ОРГАНИЗАЦИИ

Sheet Пояснит.записка
A2: Сокращенное название организации
A4: Пояснительная записка
A5: к паспорту _________________________________________
C6: полное название предприятия
A7: по состоянию на «_____»______________20_____ года
A9: Файл:
B12: Подпись
C13: должность, Ф.И.О. исполнителя и его контактный телефон

Sheet А-1
C1: Таблица А/1
A2: Сокращенное название организации
A4: Адресно-справочная информация об организации
A6: Код строки | B6: Показатель | C6: Значение показателя
A7: 1 | B7: 2 | C7: 3
A8: 100 | B8: Полное наименование организации
A9: 101 | B9: Сокращенное наименование организации
A10: 110 | B10: Юридический адрес: | C10: Х
A11: 111 | B11: Почтовый индекс
A12: 112 | B12: Республика, край, область
A13: 113 | B13: Район, населенный пункт
A14: 114 | B14: Улица, номер дома, корпус или строение
A15: 120 | B15: Почтовый адрес: | C15: X
A16: 121 | B16: Почтовый индекс
A17: 122 | B17: Республика, край, область
A18: 123 | B18: Район, населенный пункт
A19: 124 | B19: Улица, номер дома, корпус или строение
A20: 130 | B20: Телефон
A21: 131 | B21: Факс
A22: 132 | B22: Адрес электронной почты
A23: 133 | B23: Сайт организации
A24: 133 | B24: Должность, фамилия, имя, отчество руководителя
A25: 140 | B25: Когда и на каком основании (дата и номер документа) создана организация
A26: 141 | B26: Основной государственный регистрационный номер записи о создании юридического лица, внесенный в ЕГРЮЛ
A27: 142 | B27: Дата выдачи свидетельства о внесении изменений в ЕГРЮЛ
... A55: 600 | B55: Примечания
B58: Подпись
B59: должность, Ф.И.О. исполнителя и его контактный телефон

Sheet А-2
C1: I-2 | I1: Таблица А/2
A2: Сокращенное название организации
A4: Сведения о филиалах и обособленных производственных подразделениях
A6: № п/п | B6: Полное название | C6: Краткое название | D6: Почтовый адрес | H6: Специализация, основные виды выпускаемой продукции | I6: Примечания
D7: индекс | E7: республика, край, область | F7: район, населенный пункт | G7: улица, номер дома, корпус или строение
A8: 1 | B8: 2 | C8: 3 | D8: 4 | E8: 5 | F8: 6 | G8: 7 | H8: 8 | I8: 9
F12: Подпись
G13: должность, Ф.И.О. исполнителя и его контактный телефон

Sheet А-3
D1: Таблица А/3
A2: Сокращенное название организации
A4: Ситуационный план организации
A6: № п/п | B6: Имя файла | C6: Описание | D6: Примечание
A7: 1 | B7: 2 | C7: 3 | D7: 4
B12: Подпись
C13: должность, Ф.И.О. исполнителя и его контактный телефон

Sheet А-4
D1: Таблица А/4
A2: Сокращенное название организации
A4: Схема генерального плана (М 1 : 5000)
A6: № п/п | B6: Имя файла | C6: Описание | D6: Примечание
A7: 1 | B7: 2 | C7: 3 | D7: 4
B11: Подпись
C12: должность, Ф.И.О. исполнителя и его контактный телефон

Sheet А-5
D1: Таблица А/5
A2: Сокращенное название организации
A4: Организационно-структурная схема (схема управления организацией)
B9: Подпись
C10: должность, Ф.И.О. исполнителя и его контактный телефон

Sheet А-6
L1: Таблица А/6
A2: Сокращенное название организации
A4: Сведения о дочерних, в т.ч. малых предпринимательских структурах
A6: № п/п | B6: Полное и краткое наименование дочерних, в т.ч. малых предпринимательс- ких структур (по Уставу) | C6: Код ОКОПФ | D6: Состав учредителей | E6: Доля учредителей в уставном капитале, % | F6: Тип вклада учредителей в уставных капитал (денежный, оборудование, площади и т.п.) | G6: Юридический адрес (фактический адрес) | H6: Номер в Гос- реестре/дата регистрации | I6: Виды деятельности по Уставу, в т.ч. основной вид деятельности | J6: Наличие лицензии или другого разрешающего документа на работы по РКТ (номер, дата выдачи, срок действия) | K6: Годовой объем продукции (работ, услуг), млн. руб. за год
K7: всего | L7: в т.ч. РКТ
A8: 1 | B8: 2 | C8: 3 | D8: 4 | E8: 5 | F8: 6 | G8: 7 | H8: 8 | I8: 9 | J8: 10 | K8: 11 | L8: 12
H12: Подпись
I13: должность, Ф.И.О. исполнителя и его контактный телефон

Sheet А-7
K1: Таблица А/7
A2: Сокращенное название организации
A4: Сведения о ценных бумагах акционерного общества и ценных бумагах его дочерних (зависимых) обществ
A6: № п/п | B6: Наименование дочернего (зависимого) общества | C6: Категория (тип) ценных бумаг | D6: Дата выпуска (эмиссии) | E6: Объем эмиссии руб. | F6: Номинальная стоимость ценной бумаги на дату заполнения паспорта, руб. | G6: Дата (ы) изменения номинала ценных бумаг (если проводилось) и пропорции изменения, % | H6: Сроки конвертации (для конверти- руемых бумаг) | I6: Срок погашения (для облигаций) | J6: Доходность облигаций (дивиденд за последний отчетный год для акций), % к номиналу | K6: Рыночная стоимость акции (облигации) на дату заполнения паспорта (при наличии котировок), руб.
A7: 1 | B7: 2 | C7: 3 | D7: 4 | E7: 5 | F7: 6 | G7: 7 | H7: 8 | I7: 9 | J7: 10 | K7: 11
G11: Подпись
H12: должность, Ф.И.О. исполнителя и его контактный телефон

Sheet I-1
F1: Таблица I/1
A2: Сокращенное название организации
A4: Сведения о лицензиях на виды деятельности
A6: Вид деятельности | B6: Группы продукции по ЕКПС, указанные в лицензии | C6: Лицензия | F6: Срок действия лицензии
C7: номер | D7: дата | E7: кем выдана
A8: 1 | B8: 2 | C8: 3 | D8: 4 | E8: 5 | F8: 6
C12: Подпись
D13: должность, Ф.И.О. исполнителя и его контактный телефон
A14: ЕКПС - единый классификатор предметов снабжения

Sheet I-2
N1: Таблица I/2
A2: Сокращенное название организации
A4: Сведения о сертификатах соответствия (заключениях)
A6: № п/п | B6: Наименование | D6: Реквизиты | I6: Область действия | N6: Реквизиты документа, которым соответствует объект сертификации (наименование, обозначение ГОСТ, ТУ и т.д.) | O6: Номер ВП, № и дата согласования им сертификата, заключения
B7: орган по сертификации | C7: система сертификации | D7: наименование, обозначение документа | E7: номер | F7: дата выдачи | G7: срок действия | I7: наименование (сертификата, заключения) | J7: объект сертификации (система менеджмента качества, продукция, технологический процесс, производство, система управления окружающей средой, система управления охраной труда, иное) | K7: системы менеджмента качества
G8: дата начала | H8: дата окончания | K8: по видам деятельности (разработка, производство, ремонт, утилизация и т.д.) | L8: по кодам ЕКПС | M8: по кодам ОКП (по видам и типам продукции)
A9: 1 | B9: 2 | C9: 3 | D9: 4 | E9: 5 | F9: 6 | G9: 7 | H9: 8 | I9: 9 | J9: 10 | K9: 11 | L9: 12 | M9: 13 | N9: 14 | O9: 15
J14: Подпись
K15: должность, Ф.И.О. исполнителя и его контактный телефон

Sheet I-3
C1: Таблица I/3
A2: Сокращенное название организации
A4: Информация об официальном аудиторе организации
A6: № п/п | B6: Показатель | C6: Значение показателя
A7: 1 | B7: 2 | C7: 3
A8: 1 | B8: Дата проведения конкурсного отбора аудиторской организации и результаты проведения конкурса
A9: 2 | B9: Полное наименование официального аудитора, его юридический и фактический адреса, номера телефонов, факсов, электронной почты
A10: 3 | B10: Сокращенное наименование официального аудитора
A11: 4 | B11: Номер, дата выдачи и срок действия лицензии на осуществление аудиторской деятельности в соответствующей области, выданной в установленном порядке Минфином России
B14: Подпись
C15: должность, Ф.И.О. исполнителя и его контактный телефон

Sheet I-4
K1: Таблица I/4
A2: Сокращенное название организации
A4: Сведения об имущественных правах акционеров (участников) организации (холдинга)
A6: № п.п. | B6: Наименование организации | C6: ОКПО | D6: Город | E6: Имущественные права акционеров (участников) на начало и конец отчетного года
E7: акционер (участник) | F7: доля в капитале, % | H7: доля голосующих акций, % | J7: специальное право («золотая акция»)
F8: на 01 января | G8: на 31 декабря | H8: на 01 января | I8: на 31 декабря | J8: на 01 января | K8: на 31 декабря
A9: 1 | B9: 2 | C9: 3 | D9: 4 | E9: 5 | F9: 6 | G9: 7 | H9: 8 | I9: 9 | J9: 10 | K9: 11
G13: Подпись
H14: должность, Ф.И.О. исполнителя и его контактный телефон

Sheet I-5
L1: Таблица I/5
A2: Сокращенное название организации
A4: Сведения об участии в других организациях
A6: № п/п | B6: Наименование организации | C6: Доля в уставном капитале, % | E6: Доля голосующих акций, % | G6: Стоимость доли в уставном капитале, рублей | I6: Количество обыкновенных акций акций, шт. | K6: Количество привилегированных акций, шт.
C7: на 01 января | D7: на 31 декабря | E7: на 01 января | F7: на 31 декабря | G7: на 01 января | H7: на 31 декабря | I7: на 01 января | J7: на 31 декабря | K7: на 01 января | L7: на 31 декабря
A8: 1 | B8: 2 | C8: 3 | D8: 4 | E8: 5 | F8: 6 | G8: 7 | H8: 8 | I8: 9 | J8: 10 | K8: 11 | L8: 12
G12: Подпись
H13: должность, Ф.И.О. исполнителя и его контактный телефон

Sheet I-6
D1: Таблица I/6
A2: Сокращенное название организации
A4: Сведения о совете директоров общества
A6: № п/п | B6: Ф.И.О. | C6: Должность | D6: Доля акций общества, %
A7: 1 | B7: 2 | C7: 3 | D7: 4
A8: Состав совета директоров на 01.01 отчетного года
A9: Правоустанавливающий документ
A12: Дата начала работы Совета директоров в измененном составе на ____ отчетного года
A13: Правоустанавливающий документ
B18: Подпись
C19: должность, Ф.И.О. исполнителя и его контактный телефон

Sheet раздел II
A9: II. ВЫПОЛНЕНИЕ СЕРИЙНЫХ ПОСТАВОК ПРОДУКЦИИ

Sheet II-1
K1: Таблица II/1
B2: Сокращенное название организации
B4: Отчет о ходе выполнения и финансирования поставок продукции военного и специального назначения (работ, услуг) по государственному оборонному заказу
K6: Цены указываются без НДС | T6: Цены указываются без НДС | Z6: Цены указываются без НДС
A7: № п/п | B7: Продукция (работы, услуги) | E7: Государственный заказчик, заказчик | F7: Государствен- ные контракты, контракты (номер, дата и срок действия) | G7: Единица измерения количества продукции | H7: Использование базовых и критических промышленных технологий (если есть) | L7: Предусмотрено контрактами на отчетный год | N7: Предусмотрено контрактами на периоды, следующие за отчетным годом (количество) | O7: Запасы на складе на начало отчетного года (количество) | P7: Произведено за отчетный год | R7: Отгружено заказчику за отчетный год | T7: Остатки на складах на конец отчетного года (количество) | U7: Оплачено Заказчиком за отчетный год, тыс.руб | V7: Задолженность организации перед Заказчиком либо задолженность Заказчика (гр.22 со знаком минус) перед организацией на конец отчетного периода года | X7: Доля собственных работ в себестоимости продукции, (работ, услуг) (в %) | Y7: Сумма комиссий, взимаемой ОАО «Рособоронэкспорт», тыс. руб. | Z7: Примечания
B8: наименование | C8: код ОКПД 2 | D8: код ЕКПС | H8: наименование | I8: признак и вид | J8: номер | K8: шифр | L8: кол-во | M8: стоимость, тыс. руб. | P8: кол-во | Q8: стоимость, тыс. руб. | R8: кол-во | S8: стоимость, тыс. руб. | V8: кол-во | W8: стоимость, тыс. руб.
A9: 1 | B9: 2 | C9: 3 | D9: 4 | E9: 5 | F9: 6 | G9: 7 | H9: 8 | I9: 9 | J9: 10 | K9: 11 | L9: 12 | M9: 13 | N9: 14 | O9: 15 | P9: 16 | Q9: 17 | R9: 18 | S9: 19 | T9: 20 | U9: 21 | V9: 22 | W9: 23 | X9: 24 | Y9: 25 | Z9: 26
B10: 1. Поставки продукции ( работ, услуг) по государственным контрактам ГОЗ
B13: 2. Поставки продукции ( работ, услуг) по контрактам ГОЗ (соисполнительство)
B16: 3. Поставки продукции (работ, услуг) по договорам комиссии с ОАО «Рособоронэкспорт»
B19: 4. Поставка продукции (работ, услуг) по другим контрактам
W23: Подпись
X24: должность, Ф.И.О. исполнителя и его контактный телефон

Sheet II-2
I1: Таблица II/2
A2: Сокращенное название организации
A4: Выпускаемая продукция, основные технические переделы и «узкие места»
A6: № п/п | B6: Наименование выпускаемой товарной продукции | C6: Маршрут по: | D6: Наличие «узких мест» по технологическим переделам
C7: технологическим переделам | D7: причины (Кзаг., износ и пр.) | E7: предлагаемые мероприятия по их устранению | F7: срок реализации, года | H7: объем финансирования, млн.руб.
F8: начало | G8: окончание | H8: из бюджета | I8: из собственных средств
A9: 1 | B9: 2 | C9: 3 | D9: 4 | E9: 5 | F9: 6 | G9: 7 | H9: 8 | I9: 9
E13: Подпись
F14: должность, Ф.И.О. исполнителя и его контактный телефон

Sheet II-3
J1: Таблица II/3
A2: Сокращенное название организации
A4: «Узкие места» производственного процесса изделий РКТ в организации (на плановый период)
A6: № п/п | B6: Проблема, «узкое место» производства | C6: Основные мероприятия по расшивке «узкого места» | D6: Затраты | G6: Эффект от расшивки «узкого места» | H6: Основание для проведения работ | I6: Исполнители | J6: Примечание
D7: min/max по годам
D8: 1 год | E8: 2 год | F8: 3 год
A9: 1 | B9: 2 | C9: 3 | D9: 4 | E9: 5 | F9: 6 | G9: 7 | H9: 8 | I9: 9 | J9: 10
G13: Подпись
H14: должность, Ф.И.О. исполнителя и его контактный телефон

Sheet II-4
I1: Таблица II/4
A2: Сокращенное название организации
A4: Кооперационные связи организации
A6: № п/п | B6: Название поставщика, дислокация | D6: Поставляемая продукция | F6: Применяемость: | H6: Наименование изделия (товарной продукции) | I6: Предприятие потребитель изделия
B7: организация | C7: город | D7: наименование | E7: количество, шт./ в год. | F7: наименование ДСЕ | G7: количество на ДСЕ
A8: 1 | B8: 2 | C8: 3 | D8: 4 | E8: 5 | F8: 6 | G8: 7 | H8: 8 | I8: 9
F12: Подпись
G13: должность, Ф.И.О. исполнителя и его контактный телефон

Sheet раздел III
A9: III. ВЫПОЛНЕНИЕ НИОКР ПО СПЕЦПРОДУКЦИИ

Sheet III-1
K1: Таблица III/1
B2: Сокращенное название организации
B4: Сведения об участии в реализации государственных и федеральных целевых программ
K6: (тыс. рублей)
A7: № п/п | B7: Мероприятия, наименование программы (подпрограммы, ФЦП) и направления финансирования | C7: КБК | D7: Направлено на создание (применение) базовых и критических промышленных технологий | H7: Образец ВВСТ, в интересах которого выполняется работа | J7: Сроки реализации мероприятий | L7: Общий объем финансирования мероприятий программы | O7: Объем средств, израсходованных на реализацию программы, в отчетном году | R7: Объем средств, планируемых на реализацию программы в следующем году | U7: Результаты от реализации мероприятий | V7: Примечание
H8: наименование | I8: код по ОКПД2/ ЕКПС | J8: начало | K8: окончание | L8: всего | M8: в том числе за счет: | O8: всего | P8: в том числе за счет: | R8: всего | S8: в том числе за счет:
D9: наименование | E9: признак и вид | F9: номер | G9: шифр | M9: фед. бюдж. | N9: собств. средств | P9: фед. бюдж. | Q9: собств. средств | S9: фед. бюдж. | T9: собств. средств
A10: 1 | B10: 2 | C10: 3 | D10: 4 | E10: 5 | F10: 6 | G10: 7 | H10: 8 | I10: 9 | J10: 10 | K10: 11 | L10: 12 | M10: 13 | N10: 14 | O10: 15 | P10: 16 | Q10: 17 | R10: 18 | S10: 19 | T10: 20 | U10: 21 | V10: 22
B11: Наименование программы (подпрограммы, ФЦП)
B12: Мероприятие 1
B13: Наименование программы (подпрограммы, ФЦП)
B14: …
B15: Мероприятие n
B16: …
Q18: Подпись
R19: должность, Ф.И.О. исполнителя и его контактный телефон

Sheet III-2
A1: III-1 | J1: Таблица III/2
B2: Сокращенное название организации
B4: Отчет о ходе выполнения и финансирования работ НИОКР по спецпродукции
I6: ( в тыс. руб. без НДС)
A7: № п/п | B7: Вид работы | C7: Наименование работы | D7: Шифр темы | E7: Госзаказчик, (заказчик) | F7: № контракта (договора) | G7: Источник финансирования | H7: Признак и вид технологии | I7: Номер технологии | J7: Шифр технологии | K7: Образец ВВСТ в интересах которого выполнялась работа | N7: Этап ЖЦ | O7: Сроки исполнения работы в т.ч. этапа (этапов) | Q7: Полная стоимость (лимитная цена) работы | S7: Фактически оплачено с начала выполнения | U7: Объем выполненных работ за отчетный год | Y7: Ассигнования соисполнителям в отчетном году | Z7: Примечание
K8: название | L8: код ОКПД 2 | M8: код ЕКПС | O8: начало | P8: окончание | Q8: всего | R8: собств. средства | S8: всего | T8: из собств. средств | U8: план, всего | V8: план, из собств. средств | W8: факт, всего | X8: факт, из собств. средств
A10: 1 | B10: 2 | C10: 3 | D10: 4 | E10: 5 | F10: 6 | G10: 7 | H10: 8 | I10: 9 | J10: 10 | K10: 11 | L10: 12 | M10: 13 | N10: 14 | O10: 15 | P10: 16 | Q10: 17 | R10: 18 | S10: 19 | T10: 20 | U10: 21 | V10: 22 | W10: 23 | X10: 24 | Y10: 25 | Z10: 26
B11: 1. НИОКР, выполняемые по государственным и федеральным целевым программмам
B12: 1.1 Поставка научно-технической продукции по государственным контрактам
B14: 1.2 Поставка научно-технической продукции по контрактам
B17: 2. НИОКР, выполняемые по заданиям ГОЗ
B18: 2.1 Поставка научно-технической продукции по государственным контрактам
B21: 2.2 Поставка научно-технической продукции по контрактам
B24: 3. НИОКР, выполняемые по договорам ВТС
B25: 3.1 Поставка научно-технической продукции по государственным контрактам
B28: 3.2 Поставка научно-технической продукции по контрактам
B31: 4. Выполнение инициативных НИОКР (за счет собственных средств)
W34: Подпись
X35: должность, Ф.И.О. исполнителя и его контактный телефон

Sheet III-3
A1: III-1 | J1: Таблица III/3
B2: Сокращенное название организации
B4: Планируемые НИОКР по спецпродукции
J5: ( в тыс. руб. без НДС)
A6: № п/п | B6: Вид работы | C6: Наименование работы | D6: Шифр темы | E6: Госзаказчик, (заказчик) | F6: № контракта (договора) | G6: Источник финанси-рования | H6: Признак и вид технологии | I6: Номер технологии | J6: Шифр технологии | K6: Образец ВВСТ в интересах которого выполнялась работа | N6: Этап ЖЦ | O6: Сроки исполнения работы в т.ч. этапа (этапов) | Q6: Полная стоимость (лимитная цена) работы | S6: Объемы, запланированные на следующие за отчетным годы | U6: Примечание
K8: название | L8: код ОКПД 2 | M8: код ЕКПС | O8: начало | P8: окончание | Q8: всего | R8: из собств. средств | S8: всего | T8: из собств. средств
A9: 1 | B9: 2 | C9: 3 | D9: 4 | E9: 5 | F9: 6 | G9: 7 | H9: 8 | I9: 9 | J9: 10 | K9: 11 | L9: 12 | M9: 13 | N9: 14 | O9: 15 | P9: 16 | Q9: 17 | R9: 18 | S9: 19 | T9: 20 | U9: 21
B10: 1. НИОКР, выполняемые по государственным и федеральным целевым программмам
B11: 1.1 Поставка научно-технической продукции по государственным контрактам
B13: 1.2 Поставка научно-технической продукции по контрактам
B15: 2. НИОКР, выполняемые по заданиям ГОЗ
B16: 2.1 Поставка научно-технической продукции по государственным контрактам
B18: 2.2 Поставка научно-технической продукции по контрактам
B20: 3. НИОКР, выполняемые по договорам ВТС
B21: 3.1 Поставка научно-технической продукции по государственным контрактам
B23: 3.2 Поставка научно-технической продукции по контрактам
B25: 4. Выполнение инициативных НИОКР (за счет собственных средств)
Q28: Подпись
R29: должность, Ф.И.О. исполнителя и его контактный телефон

Sheet раздел IV
A9: IV. ВЫПОЛНЕНИЕ РАБОТ ПО ПРОДУКЦИИ ГРАЖДАНСКОГО НАЗНАЧЕНИЯ

Sheet IV-1
A1: IV-1 | O1: Таблица IV/1
A2: Сокращенное название организации
A4: Производство продукции гражданского назначения, товаров народного потребления и услуг, оказанных организацией
O6: Суммы указывать без НДС
A7: № п/п | B7: Наименование продукции (услуг) | C7: Код ОКПД2 | D7: Единица измерения | E7: Плановый объем производства продукции | G7: Фактический объем произведенной продукции | I7: Фактический объем реализованной продукции | K7: Объём поставок ПГН на экспорт | M7: Остатки готовой продукции на складе на конец года | O7: Примечания
E9: кол-во | F9: тыс.руб. | G9: кол-во | H9: тыс.руб. | I9: кол-во | J9: тыс.руб. | K9: кол-во | L9: тыс.руб. | M9: кол-во | N9: тыс.руб.
A10: 1 | B10: 2 | C10: 3 | D10: 4 | E10: 5 | F10: 6 | G10: 7 | H10: 8 | I10: 9 | J10: 10 | K10: 11 | L10: 12 | M10: 13 | N10: 14 | O10: 15
I14: Подпись
J15: должность, Ф.И.О. исполнителя и его контактный телефон

Sheet IV-2
C1: Таблица IV/2
A3: Сокращенное название организации
A5: Ожидаемое развитие, виды технологий и проблемы реализации программы товаров народного потребления. Выделенные производственные площади и оборудование
A7: № п/п | B7: Направления развития | C7: Решения
A8: 1 | B8: 2 | C8: 3
A9: 1 | B9: Социальные меры поддержки программы производства ПГН и ТНП
A10: 2 | B10: Ожидаемое развитие:
A11: 2.1 | B11: – по выпуску ПГН и ТНП
A12: 2.2 | B12: – по изменению состава выпускаемой продукции
A13: 2.3 | B13: – по постановке на производство новых видов ПГН и ТНП
A14: 3 | B14: Базовые технологии при производстве ПГН, ТНП и их развитие
A15: 4 | B15: Какие производственные площади используются для производства ПГН и ТНП
A16: 5 | B16: Оборудование используемое при производстве ПГН и ТНП
A17: 6 | B17: «Узкие места» при производстве ПГН и ТНП
A18: 7 | B18: Какие мероприятия планируются для расшивки «узких мест» производства ПГН и ТНП
B20: Подпись
C21: должность, Ф.И.О. исполнителя и его контактный телефон

Sheet IV-3
G1: Таблица IV/3
B2: Сокращенное название организации
B4: Инновационные проекты по продукции гражданского и двойного назначения
A6: № п/п | B6: Наименование инновационного проекта | C6: Краткое содержание проекта | D6: Код направ-ленности | E6: Степень готовности проекта | F6: Степень участия в финансировании реализации проекта, % | G6: Объем необходимых инвестиций, тыс. руб. | H6: Источники инвестиций (тыс.руб.) | L6: Сроки реализации проекта | N6: Себестоимость единицы продукции, тыс.руб. | P6: Плановый срок окупаемости проекта, лет | Q6: Рентабельность проекта, % | S6: Примечания
H7: бюджетное финанси- рование | I7: собственные средства | J7: иностранные инвестиции | K7: прочие средства | L7: начало | M7: конец | N7: плановая | O7: фактическая | Q7: плановая | R7: фактическая
A8: 1 | B8: 2 | C8: 3 | D8: 4 | E8: 5 | F8: 6 | G8: 7 | H8: 8 | I8: 9 | J8: 10 | K8: 11 | L8: 12 | M8: 13 | N8: 14 | O8: 15 | P8: 16 | Q8: 17 | R8: 18 | S8: 19
O12: Подпись
P13: должность, Ф.И.О. исполнителя и его контактный телефон

Sheet раздел V
A9: V. ВЫПОЛНЕНИЕ РАБОТ ПО ГОСУДАРСТВЕННЫМ КОНТРАКТАМ

Sheet V-1
L1: Таблица V/1
A2: Сокращенное название организации
A4: Продукция отечественных производителей, закупаемая в обеспечение выполнения государственных контрактов (контрактов)
A6: № п/п | B6: Наименовании продукции, для которой осуществлялась закупка | C6: Государственный(е) контракт(ы) (контракт(ы) | D6: Доля собственных работ в себестоимости продукции, (в %) | E6: Закупаемая продукция (материалы, комплектующие и пр.) | I6: Объем закупок | L6: Примечания
E7: наименование | F7: код ОКПД2 | G7: код ЕКПС | H7: организация-поставщик | I7: единица измерения количества продукции | J7: количество | K7: стоимость, тыс.руб
A8: 1 | B8: 2 | C8: 3 | D8: 4 | E8: 5 | F8: 6 | G8: 7 | H8: 8 | I8: 9 | J8: 10 | K8: 11 | L8: 12
H12: Подпись
I13: должность, Ф.И.О. исполнителя и его контактный телефон

Sheet V-2
L1: Таблица V/2
A2: Сокращенное название организации
A4: Продукция, импортируемая в обеспечение выполнения государственных контрактов (контрактов)
A6: № п/п | B6: Наименование продукции, для которой осуществлялась закупка | C6: Государст-венный(е) контракт(ы) (контракт(ы) | D6: Доля собственных работ в себестоимости продукции, (в %) | E6: Закупаемая продукция (материалы, комплектующие и пр.) | I6: Объем закупок | L6: Примечания
E7: наименование | F7: код ОКПД2 | G7: страна происхождения | H7: производитель | I7: единица измерения количества продукции | J7: количество | K7: стоимость, тыс. долл. США
A8: 1 | B8: 2 | C8: 3 | D8: 4 | E8: 5 | F8: 6 | G8: 7 | H8: 8 | I8: 9 | J8: 10 | K8: 11 | L8: 12
H12: Подпись
I13: должность, Ф.И.О. исполнителя и его контактный телефон

Sheet V-3
J1: Таблица V/3
A2: Сокращенное название организации
A4: Сведения о продукции (материалах и комплектующих), используемой при выполнении государственных контрактов (контрактов), производство которой прекращено (приостановлено) или находится за пределами Российской Федерации и импорт которой ограничен
A6: № п/п | B6: Продукция, при производстве которой используется | C6: Государственный контракт (контракт) | D6: Закупаемая продукция (материалы, комплектующие и пр.) | H6: Единица измерения количества | I6: Потребность | J6: Наличие на складе
D7: наименование | E7: код ОКПД2 | F7: страна происхождения | G7: производитель (бывший производитель)
A8: 1 | B8: 2 | C8: 3 | D8: 4 | E8: 5 | F8: 6 | G8: 7 | H8: 8 | I8: 9 | J8: 10
F12: Подпись
G13: должность, Ф.И.О. исполнителя и его контактный телефон

Sheet раздел VI
B9: VI. ПРОИЗВОДСТВЕННО-ТЕХНОЛОГИЧЕСКАЯ БАЗА

Sheet VI-1
A1: V-1 | K1: Таблица VI/1
B2: Сокращенное название организации
B4: Производственные основные фонды - возрастной состав оборудования
A6: Код строки | B6: Наименование оборудования по его применению в различных видах деятельности | C6: Количество оборудования на конец года ед. | F6: Из установленного оборудования – оборудование в возрасте, единиц Из установленного оборудования – оборудование в возрасте, единиц Из установленного оборудования – оборудование в возрасте, единиц | AE6: Примечание
C7: всего | D7: введенное в эксплуатацию в отчетном году | E7: импортное оборудование | F7: до 5 лет | K7: от 5 до 10 лет | P7: от 10 до 15 лет | U7: от 15 до 20 лет | Z7: свыше 20 лет
F8: всего | G8: импортного оборудования | H8: коэффициент использования оборудования в производстве | J8: средневзвешенный коэффициент загрузки | K8: всего | L8: импортного оборудования | M8: коэффициент использования оборудования в производстве | O8: средневзвешенный коэффициент загрузки | P8: всего | Q8: импортного оборудования | R8: коэффициент использования оборудования в производстве | T8: средневзвешенный коэффициент загрузки | U8: всего | V8: импортного оборудования | W8: коэффициент использования оборудования в производстве | Y8: средневзвешенный коэффициент загрузки | Z8: всего | AA8: импортного оборудования | AB8: коэффициент использования оборудования в производстве | AD8: средневзвешенный коэффициент загрузки
H9: ПВН | I9: ПГиДН | M9: ПВН | N9: ПГиДН | R9: ПВН | S9: ПГиДН | W9: ПВН | X9: ПГиДН | AB9: ПВН | AC9: ПГиДН
A10: 1 | B10: 2 | C10: 3 | D10: 4 | E10: 5 | F10: 6 | G10: 7 | H10: 8 | I10: 9 | J10: 10 | K10: 11 | L10: 12 | M10: 13 | N10: 14 | O10: 15 | P10: 16 | Q10: 17 | R10: 18 | S10: 19 | T10: 20 | U10: 21 | V10: 22 | W10: 23 | X10: 24 | Y10: 25 | Z10: 26 | AA10: 27 | AB10: 28 | AC10: 29 | AD10: 30 | AE10: 31
A11: 100 | B11: Станочный парк и оборудование всего по организации в т.ч. по видам производства:
A12: 101 | B12: Металлургическое производство
A13: 102 | B13: Производство оптических материалов и оптических сред
A14: 103 | B14: Литейное производство
A15: 104 | B15: Кузнечно-прессовое производство
A16: 105 | B16: Механообрабатывающее производство
A17: 106 | B17: Изготовление оптических деталей
A18: 107 | B18: Быстрое прототипирование и изготовление деталей на основе аддитивных технологий
A19: 108 | B19: Химическое производство
A20: 109 | B20: Гальванохимическое производство
A21: 110 | B21: Термическое и химико-термическое производство
A22: 111 | B22: Нанесение защитных покрытий
... A43: 132 | B43: Прочие виды производства
A44: 200 | B44: Уникальное станочное оборудование | H44: Х | I44: Х | J44: Х | M44: Х | N44: Х | O44: Х | R44: Х | S44: Х | T44: Х | W44: Х | X44: Х | Y44: Х | AB44: Х | AC44: Х | AD44: Х
A45: 300 | B45: Универсальные станки с ЧПУ | H45: Х | I45: Х | J45: Х | M45: Х | N45: Х | O45: Х | R45: Х | S45: Х | T45: Х | W45: Х | X45: Х | Y45: Х | AB45: Х | AC45: Х | AD45: Х
A46: 400 | B46: Гибкие производственные системы и автоматические линии | H46: Х | I46: Х | J46: Х | M46: Х | N46: Х | O46: Х | R46: Х | S46: Х | T46: Х | W46: Х | X46: Х | Y46: Х | AB46: Х | AC46: Х | AD46: Х
A47: 500 | B47: Роботы и робототехнические комплексы, программируемые манипуляторы | H47: Х | I47: Х | J47: Х | M47: Х | N47: Х | O47: Х | R47: Х | S47: Х | T47: Х | W47: Х | X47: Х | Y47: Х | AB47: Х | AC47: Х | AD47: Х
A48: 600 | B48: Количество машин, оборудования и станков, используемых в основном производстве | H48: Х | I48: Х | J48: Х | M48: Х | N48: Х | O48: Х | R48: Х | S48: Х | T48: Х | W48: Х | X48: Х | Y48: Х | AB48: Х | AC48: Х | AD48: Х
A49: 700 | B49: Объекты научно-эксперементальной стендовой базы (НЭСБ), в т.ч.: | D49: Х | E49: Х | G49: Х | H49: Х | I49: Х | J49: Х | L49: Х | M49: Х | N49: Х | O49: Х | Q49: Х | R49: Х | S49: Х | T49: Х | V49: Х | W49: Х | X49: Х | Y49: Х | AA49: Х | AB49: Х | AC49: Х | AD49: Х
A50: 710 | B50: автономные исследовательские и испытательные комплексы, в т.ч.: | D50: Х | E50: Х | G50: Х | H50: Х | I50: Х | J50: Х | L50: Х | M50: Х | N50: Х | O50: Х | Q50: Х | R50: Х | S50: Х | T50: Х | V50: Х | W50: Х | X50: Х | Y50: Х | AA50: Х | AB50: Х | AC50: Х | AD50: Х
A51: 711 | B51: внесенных в Реестр УСБ | D51: Х | E51: Х | G51: Х | H51: Х | I51: Х | J51: Х | L51: Х | M51: Х | N51: Х | O51: Х | Q51: Х | R51: Х | S51: Х | T51: Х | V51: Х | W51: Х | X51: Х | Y51: Х | AA51: Х | AB51: Х | AC51: Х | AD51: Х
A52: 720 | B52: автономные исследовательские и испытательные стенды, в т.ч.: | D52: Х | E52: Х | G52: Х | H52: Х | I52: Х | J52: Х | L52: Х | M52: Х | N52: Х | O52: Х | Q52: Х | R52: Х | S52: Х | T52: Х | V52: Х | W52: Х | X52: Х | Y52: Х | AA52: Х | AB52: Х | AC52: Х | AD52: Х
A53: 721 | B53: внесенных в Реестр УСБ | D53: Х | E53: Х | G53: Х | H53: Х | I53: Х | J53: Х | L53: Х | M53: Х | N53: Х | O53: Х | Q53: Х | R53: Х | S53: Х | T53: Х | V53: Х | W53: Х | X53: Х | Y53: Х | AA53: Х | AB53: Х | AC53: Х | AD53: Х
AB56: Подпись
AC57: должность, Ф.И.О. исполнителя и его контактный телефон

Sheet VI-2
I1: Таблица VI/2
B2: Сокращенное название организации
B4: Кодифицированный перечень подразделений по видам производства
A7: № п/п | B7: Наименование производственного подразделения | C7: Код подразделения | D7: Назначение | E7: Конечная продукция, в производстве которой участвует | F7: Направления предметной специализации организационно выделенных технологических мощностей (по видам конечной продукции, в производстве которой участвует) | H7: Занимаемая площадь | J7: Общая численность работающих | V7: Примечание
H8: всего | I8: производст-венная | J8: всего | K8: из них женщин | L8: ОПП | N8: вспомогательные рабочие | O8: руководители | P8: специалисты | U8: МОП
F9: код ОКВЭД 2 | G9: код ОКПД 2 | L9: станочники | M9: слесари | P9: исследователи | Q9: конструкторы | R9: технологи | S9: экономисты | T9: прочие
A10: 1 | B10: 2 | C10: 3 | D10: 4 | E10: 5 | F10: 6 | G10: 7 | H10: 8 | I10: 9 | J10: 10 | K10: 11 | L10: 12 | M10: 13 | N10: 14 | O10: 15 | P10: 16 | Q10: 17 | R10: 18 | S10: 19 | T10: 20 | U10: 21 | V10: 22
N14: Подпись
O15: должность, Ф.И.О. исполнителя и его контактный телефон

Sheet VI-3
J1: Таблица VI/3
B2: Сокращенное название организации
B4: Состав оборудования организации по видам производств
A6: № п/п | B6: Наименование технологии | C6: Код производственного подразделения (в соответствии с формой VI/2) | D6: Технологический процесс | F6: Группа оборудования | H6: Единица оборудования | K6: Единица оборудования (продолжение) | T6: Производственная мощность | V6: Размер | Y6: Используемое оборудование по группам | AB6: Коэффициент использования оборудования при производстве гражданской продукции (Кисп. ГП) | AC6: Коэффициент использования оборудования при производстве продукции РКТ (Кисп. РКТ) | AD6: Коэффициент загрузки оборудования при 2-сменной работе (Кзагр. ) | AE6: Средний нормативный срок эксплуатации, лет | AF6: Дата ввода в эксплуа-тации | AG6: Дата последнего капитального ремонта | AH6: Фактический износ (%) | AI6: Остаточная стоимость | AJ6: Форма приобретения (в собствен-ность, лизинг, аренда, др.) | AK6: Для оборудования, приобретенного в рамках выполнения мероприятий государственных (федеральных целевых) программ | AO6: Примечание
D7: наименование | E7: код | F7: наименование | G7: код ОКОФ | H7: идентифика-ционный код | I7: инвентарный номер | J7: наименование по техническому паспорту | K7: назначение и краткая характеристика | L7: технические характеристики конечной продукции, обрабатываемого материала, сырья, изделия, предмета обработки (изготовления) | M7: производитель (завод, фирма) | N7: страна | O7: серийный (заводской) номер | P7: год выпуска | Q7: наличие ЧПУ | R7: производитель ЧПУ | S7: дата при-обретения | T7: единица измерения | U7: значение | V7: единица измерения | W7: мин. | X7: макс. | Y7: тип | Z7: кол-во единиц | AA7: дополнитель-ные характерис-тики | AK7: государст-венная программа | AL7: источник финанси-рования приобре-тения | AM7: наименование инвестиционного проекта в соотвествии с проектно-сметной документацией | AN7: номер и дата заключения комиссии Минпромторга России об обоснованности приобретения импортного оборудования (в рамках Постановления Правительства РФ от 24.12.2013 № 1224)
A8: 1 | B8: 2 | C8: 3 | D8: 4 | E8: 5 | F8: 6 | G8: 7 | H8: 8 | I8: 9 | J8: 10 | K8: 11 | L8: 12 | M8: 13 | N8: 14 | O8: 15 | P8: 16 | Q8: 17 | R8: 18 | S8: 19 | T8: 20 | U8: 21 | V8: 22 | W8: 23 | X8: 24 | Y8: 25 | Z8: 26 | AA8: 27 | AB8: 28 | AC8: 29 | AD8: 30 | AE8: 31 | AF8: 32 | AG8: 33 | AH8: 34 | AI8: 35 | AJ8: 36 | AK8: 37 | AL8: 38 | AM8: 39 | AN8: 40 | AO8: 41
AM14: Подпись
AN15: должность, Ф.И.О. исполнителя и его контактный телефон

Sheet VI-4
K1: Таблица VI/4 | T1: Таблица VI/4
B3: Сокращенное название организации
C5: Трудоемкость годовой программы товарного выпуска продукции по видам производств
A7: № п/п | B7: Виды производств организации | C7: Трудоемкость товарной продукции по видам производств, тыс. н/час. | L7: Трудоемкость товарной продукции по видам производств, тыс. н/час. | S7: Мощность по производствам, тыс. н/час. | T7: К исп.
A9: 1 | B9: 2 | C9: 3 | D9: 4 | E9: 5 | F9: 6 | G9: 7 | H9: 8 | I9: 9 | J9: 10 | K9: 11 | L9: 12 | M9: 13 | N9: 14 | O9: 15 | P9: 16 | Q9: 17 | R9: 18 | S9: 19 | T9: 20
A10: 1 | B10: Механообрабатывающее
A11: 2 | B11: Литейное
A12: 3 | B12: Кузнечно-прессовое
A13: 4 | B13: Слесарно-каркасное
A14: 5 | B14: Гальванохимические и лакокрасочные покрытия
A15: 6 | B15: Переработка полимерных материалов
A16: 7 | B16: Изоляционное
A17: 8 | B17: Печатных плат
A18: 9 | B18: Приборов микроэлектроники
A19: 10 | B19: Сборочно-монтажное
A20: 11 | B20: Изделий из керамики и ферритов
A21: 12 | B21: Электроэлементов
A22: 13 | B22: Химическое
B24: Всего, тыс. н/час.
B25: Годовой объем выпуска, шт.(т)
P27: Подпись: | Q27: ______________________________________________
Q28: должность, Ф.И.О. исполнителя и его контактный телефон

Sheet VI-5
M1: Таблица VI/5
B2: Сокращенное название организации
B3: Сведения о приобретенном оборудовании в отчетном году
A5: № п/п | B5: Единица оборудования | F5: Источник финансиро-вания | G5: Государстве- нная программа | H5: Наименование инвестиционного проекта в соотвествии с проектно-сметной документацией | I5: Цех установки, производ-ство | J5: Коэффициент обновления оборудо-вания в цехе | K5: Обоснование приобретения оборудование | M5: Примечание
B6: наименование | C6: серийный (заводской) номер | D6: поставщик оборудования | E6: стоимость (тыс. руб.) | K6: номер | L6: дата
A7: 1 | B7: 2 | C7: 3 | D7: 4 | E7: 5 | F7: 6 | G7: 7 | H7: 8 | I7: 9 | J7: 10 | K7: 11 | L7: 12 | M7: 13
H11: Подпись
I12: должность, Ф.И.О. исполнителя и его контактный телефон

Sheet VI-6
H1: ТаблицаVI/6
B2: Сокращенное название организации
B4: Сведения об оборудовании, запланированном к закупке
H6: (цены с НДС)
A7: № п/п | B7: Технологический процесс | D7: Единица оборудования Единица оборудования (продолжение) | L7: Источник финансирования | M7: Государственная программа | N7: Наименование инвестиционного проекта в соотвествии с проектно-сметной документацией | O7: Планируемый год приобретения | P7: Цена за единицу, тыс. руб. | Q7: Кол-во, шт. | R7: Общая стоимость, тыс. руб. | S7: Номер и дата заключения комиссии Минпромторга России об обоснованности приобретения импортного оборудования (в рамках Постановления Правительства РФ от 24.12.2013 № 1224) | T7: Примечание
B8: наименование | C8: код | D8: наименование | E8: модель | F8: изготовитель | G8: поставщик | H8: страна происхождения | I8: назначение и краткая характеристика | J8: наличие ЧПУ | K8: производитель ЧПУ
A9: 1 | B9: 2 | C9: 3 | D9: 4 | E9: 5 | F9: 6 | G9: 7 | H9: 8 | I9: 9 | J9: 10 | K9: 11 | L9: 12 | M9: 13 | N9: 14 | O9: 15 | P9: 16 | Q9: 17 | R9: 18 | S9: 19 | T9: 20
R15: Подпись
S16: должность, Ф.И.О. исполнителя и его контактный телефон

Sheet VI-7
H1: Таблица VI/7
B2: Сокращенное название организации
B3: Данные по инвестиционным проектам
A5: № п/п | B5: Наименование проекта | C5: Краткая характеристика проекта | D5: Стадия разработки проекта или этап его осуществления | E5: Стоимость проекта (млн. руб) | F5: Период реализации | H5: Расчетный срок окупаемости, лет | I5: Долевое участие основных участников проекта | K5: Распределение финансирования | M5: Степень реализации проекта (%) | N5: Фактические затраты каждого участника проекта на конец отчетного года
F6: начало | G6: окончание | I6: участник | J6: % | K6: источник | L6: %
A7: 1 | B7: 2 | C7: 3 | D7: 4 | E7: 5 | F7: 6 | G7: 7 | H7: 8 | I7: 9 | J7: 10 | K7: 11 | L7: 12 | M7: 13 | N7: 14
I11: Подпись
J12: должность, Ф.И.О. исполнителя и его контактный телефон

Sheet VI-8
K1: Таблица VI/8
B2: Сокращенное название организации
A4: Сведения об арендованном (лизинговом) и полученном на ответственное хранение оборудовании за отчетный год
A6: № п/п | B6: Наименование оборудования | C6: Техпроцесс | E6: Количество оборудования (единиц) взятых в аренду | F6: Наименования организации арендодателя с указанием в каких целях используется арендованное оборудование | G6: Вид аренды, № арендных договоров и срок их действия | H6: Затраты на аренду оборудования (тыс. руб.) | K6: Примечания
C7: наименование | D7: код | H7: начислено в отчётном году | I7: факт за отчётный год | J7: план на текущий год
A8: 1 | B8: 2 | C8: 3 | D8: 4 | E8: 5 | F8: 6 | G8: 7 | H8: 8 | I8: 9 | J8: 10 | K8: 11
A9: 1
A10: 2
A11: 3
G13: Подпись | H13: __________________________________________________
H14: должность, Ф.И.О. исполнителя и его контактный телефон

Sheet VI-9
I1: Таблица VI/9
A2: ='VI-7'!B2 -> Сокращенное название организации
B4: Сведения об оборудовании, переданном в залог или обременённом иным образом (за исключением оборудования, сданного в аренду) в отчетном году
I6: (тыс. руб.)
A7: № п/п | B7: Наименование оборудования | C7: Инвентарный номер | D7: Наименование организаций-кредиторов | E7: Причины обременения с указанием соответствующих документов | F7: Сроки обременения | G7: Рыночная стоимость | H7: Сумма обязательств (кредитов, займов, исков и т.д.) | I7: Примечания
A8: 1 | B8: 2 | C8: 3 | D8: 4 | E8: 5 | F8: 6 | G8: 7 | H8: 8 | I8: 9
E12: Подпись
F13: должность, Ф.И.О. исполнителя и его контактный телефон

Sheet VI-10
I1: Таблица VI/10
A2: Сокращенное название организации
A4: Сведения об оборудовании организации, сданном в аренду в отчетном году
A6: № п/п | B6: Наименование оборудования, сдававшегося в аренду в течение отчётного года | C6: Количество оборудования (единиц), сданного в аренду | D6: Наименования организаций-арендаторов, с указанием в каких целях используется арендованное оборудование | E6: Вид аренды, № арендных договоров и срок их действия | F6: Остаточная стоимость (тыс. руб.) на начало отчётного года | G6: Доходы, полученные от сдачи оборудования в аренду (тыс. руб.)
G8: начислено в отчётном году | H8: факт за отчётный год | I8: план на текущий год
A13: 1 | B13: 2 | C13: 3 | D13: 4 | E13: 5 | F13: 6 | G13: 7 | H13: 8 | I13: 9
A16: ИТОГО:
E18: Подпись
F19: должность, Ф.И.О. исполнителя и его контактный телефон

Sheet VI-11
M1: Таблица VI/11
B2: ='VI-9'!A2 -> Сокращенное название организации
A4: Сведения об оборудовании, реализованном и списанном (утилизированном) в отчетном году и планируемом к реализации и списанию (утилизации)
A7: № п/п | B7: Наименование оборудования | C7: Количество оборудования | D7: ОКОФ | E7: Обоснование решения о реализации со ссылкой на соответствующие документы (решения) | F7: Наименование организаций-покупателей | G7: Даты заключения договоров о реализации | H7: Дата реализации | I7: Стоимость (тыс.руб.) | K7: Доходы от реализации за отчетный год (тыс.руб.) | M7: Примечания
I8: остаточная на дату реализации | J8: реализации
K9: план | L9: факт
A10: 1 | B10: 2 | C10: 3 | D10: 4 | E10: 5 | F10: 6 | G10: 7 | H10: 8 | I10: 9 | J10: 10 | K10: 11 | L10: 12 | M10: 13
A11: 1) реализованное оборудование за отчетный год
A12: 1 | B12: 2 | C12: 3 | E12: 4 | F12: 5 | G12: 6 | H12: 7 | I12: 8 | J12: 9 | L12: 10
A15: 2) оборудование, планируемое к реализации в следующем за отчетным году
A18: 3) списанное (утилизированное) оборудование в отчетном году
A21: 4) оборудование, планируемое к списанию (утилизации) в следующем за отчетным году
G27: Подпись
H28: должность, Ф.И.О. исполнителя и его контактный телефон

Sheet VI-12
N1: Таблица VI/12
A2: Сокращенное название организации
B3: Наличие испытательных площадок (полигонов)
A5: № п/п | B5: Объект | C5: Характер проводимых работ | D5: Наличие сооружений, площади и их назначение | G5: Имеющееся стандартное, нестандартное, специальное и испытательное оборудование | J5: Количество оборудования по возрасту, единиц
D6: № п/п | E6: площадь, кв.м | F6: назначение | G6: тип | H6: кол-во | I6: назначение | J6: до 5 лет | K6: от 5 до 10 лет | L6: от 10 до 15 лет | M6: от 15 до 20 лет | N6: св. 20 лет
A7: 1 | B7: 2 | C7: 3 | D7: 4 | E7: 5 | F7: 6 | G7: 7 | H7: 8 | I7: 9 | J7: 10 | K7: 11 | L7: 12 | M7: 13 | N7: 14
A8: 1 | B8: Объект А
A10: 2 | B10: Объект Б
A11: …
A12: ИТОГО: | F12: Х | G12: Х | I12: Х
H14: Подпись
I15: должность, Ф.И.О. исполнителя и его контактный телефон

Sheet VI-13
A1: XII-2 | G1: Таблица VI/13
B2: Сокращенное название организации
A4: Сводные сведения о стендово-испытательной базе
A6: Код строки | B6: Показатель | C6: Единица измерения | D6: Значение за отчетный год | E6: Плановое значение на следующий за отчетным год | F6: Прогнозные значения
F7: 2-й за отчетным год | G7: 3-й за отчетным год
A8: 1 | B8: 2 | C8: 3 | D8: 4 | E8: 5 | F8: 6 | G8: 7
A9: 100 | B9: Специализация организации, основные виды исследований (испытаний) | C9: –
A10: 200 | B10: Количество объектов научно-эксперементальной стендовой базы (НЭСБ), в т.ч.: | C10: шт.
A11: 210 | B11: внесенных в Реестр уникальной стендовой и испытательной базы (УСБ) Минпромторга России, в том числе: | C11: шт.
A12: 211 | B12: количество объектов УСБ, находящихся на хранении по сохранным распискам заказчика | C12: шт.
A13: 300 | B13: Количество автономных исследовательских и испытательных комплексов, в т.ч.: | C13: шт.
A14: 310 | B14: внесенных в Реестр УСБ | C14: шт.
A15: 320 | B15: количество стендов, входящих в состав испытательных комплексов, в т.ч.: | C15: шт.
A16: 321 | B16: внесенных в Реестр УСБ | C16: шт.
A17: 400 | B17: Количество автономных исследовательских и испытательных стендов, в том числе: | C17: шт.
A18: 410 | B18: внесенных в Реестр УСБ | C18: шт.
A19: 500 | B19: Количество остальных объектов (уровень «Г») НЭСБ | C19: шт.
A20: 600 | B20: Стоимость работ, связанных с использованием объектов УСБ, в т.ч.: | C20: тыс. руб.
... A30: 620 | B30: Справочно. Среднемесячная заработная плата работников, занятых на объектах УСБ | C30: тыс. руб.
A31: 700 | B31: Забалансовая стоимость объектов УСБ | C31: тыс. руб. | F31: X | G31: X
A32: 800 | B32: Штатная численность работников, занятых на объектах НЭСБ, в т.ч.: | C32: человек
A33: 801 | B33: на объектах УСБ | C33: человек
A34: 810 | B34: Фактическая численность работников, занятых на объектах НЭСБ, в т.ч.: | C34: человек
A35: 811 | B35: на объектах УСБ | C35: человек
A36: 900 | B36: Средний коэффициент загрузки объектов НЭСБ | C36: –
A37: 910 | B37: Коэффициент использования в производстве ПВН | C37: %
A38: Примечание:
A39: * - УСБ - уникальная стендовая и испытательная база.
D42: Подпись
E43: должность, Ф.И.О. исполнителя и его контактный телефон

Sheet раздел VII
A9: VII. ФИНАНСОВО-ЭКОНОМИЧЕСКАЯ ДЕЯТЕЛЬНОСТЬ

Sheet VII-1
A1: VI-1 | D1: Таблица VII/1
B2: Сокращенное название организации
A4: Бюджет доходов и расходов за отчетный год
D5: (тыс. руб.)
A6: Код строки | B6: Показатели | C6: Всего за отчетный год | D6: За предыдущий отчетному год
A8: 1 | B8: 2 | C8: 3 | D8: 4
A9: 1000 | B9: Выручка
A10: 1001 | B10: Реализация заказов, по которым организация является держателем контракта (головным исполнителем)
A11: 1002 | B11: Реализация заказов, по которым организация входит в кооперацию головного исполнителя из ИС
A12: 1003 | B12: Реализация заказов по внешней кооперации
A13: 1100 | B13: Выручка в рамках выполнения ГОЗ и ВТС
A14: 1110 | B14: На внутреннем рынке, в т.ч.:
A15: 1111 | B15: Реализация заказов, по которым организация является держателем контракта (головным исполнителем)
A16: 1112 | B16: Реализация заказов, по которым организация входит в кооперацию головного исполнителя из ИС
A17: 1113 | B17: Реализация заказов по внешней кооперации
A18: 1120 | B18: На экспорт, в т.ч.:
A19: 1121 | B19: Реализация заказов, по которым организация является держателем контракта (головным исполнителем)
A20: 1122 | B20: Реализация заказов, по которым организация входит в кооперацию головного исполнителя из ИС
... A43: 5000 | B43: Чистая прибыль (убыток)
A44: Справка по структуре доходов и поступлений
A45: 6001 | B45: Доходы от аренды недвижимости (за исключением объектов социальной сферы)
A46: 6002 | B46: Доходы от аренды других основных средств (за исключением объектов социальной сферы)
A47: 6003 | B47: Доходы от реализации недвижимости и других основных средств, нематериальных активов
A48: 6004 | B48: Доходы от деятельности объектов социальной сферы
A49: 6005 | B49: Проценты по кредитам и займам к получению
A50: 6006 | B50: Взносы в уставной капитал
A51: Справка по структуре расходов
A52: 7001 | B52: Расходы, связанные с арендой недвижимости (за исключением объектов социальной сферы)
A53: 7002 | B53: Расходы, связанные с арендой других основных средств (за исключением объектов социальной сферы)
A54: 7003 | B54: Расходы, связанные со списанием (ликвидацией) недвижимости и других основных средств
A55: 7004 | B55: Расходы на содержание объектов социальной сферы
B58: Подпись
D59: должность, Ф.И.О. исполнителя и его контактный телефон

Sheet VII-2
D1: Таблица VII/2
B3: Сокращенное название организации
A5: Бюджет движения денежных средств
D6: (тыс. руб.)
A7: Код строки | B7: Показатели | C7: Всего за отчетный год | D7: За предыдущий отчетному год
A8: 1 | B8: 2 | C8: 3 | D8: 4
A9: 1 | B9: Остаток денежных средств на начало периода
A10: 2 | B10: Текущая деятельность | C10: Х | D10: Х
A11: 3 | B11: Поступления от текущей деятельности (стр. 3.1 + стр. 3.2 + стр. 3.3 + стр. 3.4 + стр. 3.5 + стр. 3.6)
A12: 3.1 | B12: Поступления по основной предписанной деятельности (стр. 3.1.1 + 3.1.2)
A13: 3.1.1 | B13: На внутреннем рынке
A14: 3.1.2 | B14: На экспорт
A15: 3.2 | B15: Поступления по основной централизованной деятельности (стр. 3.2.1 + стр. 3.2.2)
A16: 3.2.1 | B16: На внутреннем рынке
A17: 3.2.2 | B17: На экспорт
A18: 3.3 | B18: Поступления по деятельности в области продукции гражданского назначения (стр. 3.3.1 + стр. 3.3.2)
A19: 3.3.1 | B19: На внутреннем рынке
A20: 3.3.2 | B20: На экспорт
A21: 3.4 | B21: Поступления от аренды недвижимости
A22: 3.5 | B22: Поступления от аренды других основных средств
A23: 3.6 | B23: Прочие поступления по текущей деятельности
A24: 4 | B24: Выплаты по текущей деятельности (стр. 4.1 + стр. 4.2 + стр. 4.3 + стр. 4.4 + стр. 4.5)
A25: 4.1 | B25: Выплаты за материальные ресурсы (стр. 4.1.1 + 4.1.2 + 4.1.3 + 4.1.4 + 4.1.5 + 4.1.6)
A26: 4.1.1 | B26: Выплаты за материалы (стр. 4.1.1.1 + стр. 4.1.1.2)
A27: 4.1.1.1 | B27: Выплаты за материалы на производство продукции (работ, услуг)
A28: 4.1.1.2 | B28: Выплаты за прочие материалы
A29: 4.1.2 | B29: Выплаты за покупные комплектующие изделия
A30: 4.1.3 | B30: Выплаты за полуфабрикаты
A31: 4.1.4 | B31: Выплаты за спецоборудование для экспериментальных работ
A32: 4.1.5 | B32: Выплаты за инвентарь и хозяйственные принадлежности
A33: 4.1.6 | B33: Выплаты за топливо и энергию
A34: 4.2 | B34: Оплата труда (стр. 4.2.1 + 4.2.2)
A35: 4.2.1 | B35: Оплата труда постоянного персонала
A36: 4.2.2 | B36: Оплата труда временно привлеченного персонала
... A51: 4.5 | B51: Прочие выплаты по текущей деятельности
A52: 5 | B52: Сальдо по текущей деятельности (стр. 3 - стр. 4)
A53: 6 | B53: Инвестиционная деятельность | C53: Х | D53: Х
A54: 7 | B54: Поступления от инвестиционной деятельности (стр. 7.1 + стр. 7.2 + стр. 7.3 + стр. 7.4 + стр. 7.5 + стр. 7.6 + стр. 7.7)
A55: 7.1 | B55: Поступления от реализации недвижимости и других основных средств, нематериальных активов
A56: 7.2 | B56: Возврат долгосрочных займов, поступления от реализации ценных бумаг, долей участия, других долгосрочных финансовых вложений (стр. 7.2.1 + стр. 7.2.2)
A57: 7.2.1 | B57: внутри группы
A58: 7.2.2 | B58: вне группы
A59: 7.3 | B59: Возврат краткосрочных займов, поступления от реализации других краткосрочных финансовых вложений (стр. 7.3.1 + стр. 7.3.2)
A60: 7.3.1 | B60: внутри группы
A61: 7.3.2 | B61: вне группы
A62: 7.4 | B62: Проценты по выданным ранее займам
A63: 7.5 | B63: Полученные дивиденды (стр. 7.5.1 + стр. 7.5.2)
A64: 7.5.1 | B64: внутри группы
A65: 7.5.2 | B65: вне группы
A66: 7.6 | B66: Целевое финансирование
A67: 7.7 | B67: Прочие поступления от инвестиционной деятельности
A68: 8 | B68: Выплаты по инвестиционной деятельности (стр. 8.1 + стр. 8.2 + стр. 8.3 + стр. 8.4 + стр. 8.5 + стр. 8.6 + стр. 8.7)
A69: 8.1 | B69: Приобретение объектов основных средств
A70: 8.2 | B70: Услуги сторонних организаций по строительным и монтажным работам
A71: 8.3 | B71: Приобретение объектов нематериальных активов
A72: 8.4 | B72: Услуги сторонних организаций по выполнению собственных НИОКР
A73: 8.5 | B73: Выдача долгосрочных займов, приобретение ценных бумаг, долей участия и другие долгосрочные финансовые вложения
A74: 8.6 | B74: Выдача краткосрочных займов, другие краткосрочные финансовые вложения
A75: 8.7 | B75: Прочие выплаты по инвестиционной деятельности
A76: 9 | B76: Сальдо по инвестиционной деятельности (стр. 7 - стр. 8)
A77: 10 | B77: Финансовая деятельность | C77: Х | D77: Х
A78: 11 | B78: Поступления от финансовой деятельности (стр. 11.1 + стр. 11.2 + стр. 11.3)
A79: 11.1 | B79: Получение долгосрочных кредитов и займов
A80: 11.2 | B80: Получение краткосрочных кредитов и займов
A81: 11.3 | B81: Прочие поступления от финансовой деятельности
A82: 12 | B82: Выплаты по финансовой деятельности (стр. 12.1 + стр. 12.2 + стр. 12.3 + стр. 12.4)
A83: 12.1 | B83: Возврат долгосрочных кредитов и займов
A84: 12.2 | B84: Возврат краткосрочных кредитов и займов
A85: 12.3 | B85: Проценты по кредитам и займам
A86: 12.4 | B86: Прочие выплаты по финансовой деятельности
A87: 13 | B87: Сальдо по финансовой деятельности (стр. 11 - стр. 12)
A88: 14 | B88: Положительные курсовые разницы
A89: 15 | B89: Отрицательные курсовые разницы
A90: 16 | B90: Остаток денежных средств на конец периода (стр. 1 + стр. 5 + стр. 9 + стр. 13 + стр. 14 - стр. 15)
A92: 17 | B92: Справочно:
A93: 17.1 | B93: НДС начисленный (сумма строк от 17.1.1 до 17.1.5)
A94: 17.1.1 | B94: НДС начисленный (выручка)
A95: 17.1.2 | B95: НДС начисленный (полученные авансы по основной деятельности)
A96: 17.1.3 | B96: НДС начисленный (полученные авансы по аренде)
A97: 17.1.4 | B97: НДС начисленный (полученные авансы по реализации ОС и НМА)
A98: 17.1.5 | B98: НДС начисленный по прочей выручке и авансам
A99: 17.2 | B99: Вычеты по НДС (сумма строк от 17.2.1 до 17.2.6)
A100: 17.2.1 | B100: Вычеты НДС с авансов по основной деятельности
A101: 17.2.2 | B101: Вычеты НДС с авансов по аренде
A102: 17.2.3 | B102: Вычеты НДС с авансов по реализации ОС и НМА
A103: 17.2.4 | B103: Вычеты по НДС с контрагентских работ
A104: 17.2.5 | B104: Вычеты по НДС с капиталовложений
A105: 17.2.6 | B105: Прочие вычеты по НДС
B108: Подпись
C109: должность, Ф.И.О. исполнителя и его контактный телефон

Sheet VII-3
Q1: Таблица VII/3
B2: Сокращенное название организации
A4: Сведения о начисленных и уплаченных налогах, сборах и страховых взносах
Q5: (тыс. руб.)
A6: № п/п | B6: Наименование налогов, сборов и страховых взносов | C6: Задолженность по налогам, сборам и страховым взносам на начало отчетного года | G6: Начисленные за период налоги, сборы и страховые взносы | J6: Уплаченные в отчетном периоде налоги, сборы и страховые взносы | N6: Задолженность по налогам, сборам и страховым взносам на конец отчетного года
C7: всего | D7: в том числе | G7: всего | H7: в том числе: | J7: всего | K7: в том числе | N7: всего | O7: в том числе
D8: федеральный бюджет | E8: региональный бюджет | F8: местный бюджет | H8: налоги, сборы, страховые взносы | I8: штрафы и пени | K8: федеральный бюджет | L8: региональный бюджет | M8: местный бюджет | O8: федеральный бюджет | P8: региональный бюджет | Q8: местный бюджет
A9: 1 | B9: 2 | C9: 3 | D9: 4 | E9: 5 | F9: 6 | G9: 7 | H9: 8 | I9: 9 | J9: 10 | K9: 11 | L9: 12 | M9: 13 | N9: 14 | O9: 15 | P9: 16 | Q9: 17
K15: Подпись
L16: должность, Ф.И.О. исполнителя и его контактный телефон

Sheet VII-4
J1: Таблица VII/4
A3: Сокращенное название организации
A5: Информация о долгосрочных финансовых вложениях в другие организации
A7: № п/п | B7: Полное и сокращенное наименование организации | C7: Юридичес- кий и почто- вый адреса организации, телефон | D7: Ф.И.О. руководи- теля | E7: Год приобре-тения акций (доли) | F7: Учреждение организации | I7: Текущая сфера деятель- ности | J7: Участие организации в основной деятельности предприятия | K7: Уставный капитал организа- ции, тыс.руб. | L7: Доля предприятия в уставном капитале организации | N7: Выручка организации, тыс. руб. | O7: Чистая прибыль организации, тыс. руб. | P7: Дивиденды, тыс. руб.
F8: год | G8: форма взноса | H8: сфера деятельности | L8: тыс.руб. | M8: % | P8: отчетный год | Q8: следующий год
A9: 1 | B9: 2 | C9: 3 | D9: 4 | E9: 5 | F9: 6 | G9: 7 | H9: 8 | I9: 9 | J9: 10 | K9: 11 | L9: 12 | M9: 13 | N9: 14 | O9: 15 | P9: 16 | Q9: 17
A12: ИТОГО:
M14: Подпись
N15: должность, Ф.И.О. исполнителя и его контактный телефон

Sheet VII-5
H1: Таблица VII/5
B2: Сокращенное название организации
A4: Сведения о дебиторской задолженности
H5: (тыс.руб. без учета НДС)
A6: Код строки | B6: Наименование | C6: На конец отчетного года | H6: На конец предыдущего отчетному года
C7: всего | D7: краткосро- чная | E7: долгосроч- ная | F7: просроче- нная | G7: нереальная к взысканию просроченная задолженность
A8: 1 | B8: 2 | C8: 3 | D8: 4 | E8: 5 | F8: 6 | G8: 7 | H8: 8
A9: 100 | B9: Дебиторская задолженность, всего:
A10: 200 | B10: Задолженность покупателей и заказчиков, в том числе:
A11: 201 | B11: авансы выданные
A12: 202 | B12: государственных заказчиков по заключенным государственным контрактам
A13: 203 | B13: по расчетам с дочерними и зависимыми обществами по всем видам операций
A14: 204 | B14: по коммунальным платежам, платежам за тепло- и энергообеспече-ние и т.п.
A15: 205 | B15: по штрафам, пеням и неустойкам, признанным или по которым получены решения суда
A16: 206 | B16: прочее
A17: 300 | B17: Задолженность работников организации
A18: 400 | B18: Задолженность по налогам и сборам всего, в том числе:
A19: 401 | B19: федеральный бюджет
A20: 402 | B20: бюджет субъекта РФ
... A29: 800 | B29: Справочно: Резервы по сомнительным долгам
D31: Подпись
E32: должность, Ф.И.О. исполнителя и его контактный телефон

Sheet VII-6
G1: Таблица VII/6
B2: Сокращенное название организации
A4: Сведения о кредиторской задолженности
G6: (тыс.руб. без учета НДС)
A7: Код строки | B7: Наименование | C7: На конец отчетного года | G7: На конец предыдущего года
C8: всего | D8: краткосрочная | E8: долгосрочная | F8: просроченная
A9: 1 | B9: 2 | C9: 3 | D9: 4 | E9: 5 | F9: 6 | G9: 7
A10: 100 | B10: Кредиторская задолженность всего, в том числе:
A11: 110 | B11: Задолженность поставщикам и подрядчикам всего, в том числе:
A12: 111 | B12: авансы полученные
A13: 112 | B13: государственным заказчикам по заключенным государственным контрактам
A14: 113 | B14: по расчетам с дочерними и зависимыми обществами по всем видам операций
A15: 114 | B15: по коммунальным платежам, платежам за тепло- и энергообеспечение и т.п.
A16: 115 | B16: по штрафам, пеням и неустойкам, признанным или по которым получены решения суда
A17: 116 | B17: задолженность прочая
A18: 120 | B18: Задолженность по оплате труда
A19: 130 | B19: Задолженность по налогам и сборам всего, в том числе:
A20: 131 | B20: перед федеральным бюджетом
A21: 132 | B21: перед бюджетом субъектов РФ
... A29: 160 | B29: Списанная задолженность
C31: Подпись
D32: должность, Ф.И.О. исполнителя и его контактный телефон

Sheet VII-7
H1: Таблица VII/7
B2: Сокращенное название организации
A4: Сведения о субсидиях и бюджетных средствах
H6: (тыс.руб.)
A7: Код строки | B7: Наименование | C7: Остаток (перерасход) субсидий и бюджетных средств на начало отчетного периода | D7: Предусмотрено (выделенный лимит, плановый объем) субсидий и бюджетных средств в отчетном году | E7: Поступило (фактический объем) субсидий и бюджетных средств в отчетном году | F7: Использовано (фактические расходы) субсидий и бюджетных средств в отчетном году | G7: Возвращено субсидий и бюджетных средств распорядителю средств (бюджету) в отчетном году | H7: Остаток (перерасход) субсидий и бюджетных средств на конец отчетного периода
A8: 1 | B8: 2 | C8: 3 | D8: 4 | E8: 5 | F8: 6 | G8: 7 | H8: 8
A9: 100 | B9: Общий объем средств субсидий и бюджетных средств всего, в том числе полученных:
A10: 101 | B10: на возмещение части затрат на уплату процентов по кредитам
A11: 102 | B11: в целях предупреждения банкротства
A12: 103 | B12: на осуществление капитальных вложений
A13: 104 | B13: на иные цели
E15: Подпись
F16: должность, Ф.И.О. исполнителя и его контактный телефон

Sheet VII-8
E1: Таблица VII/8
A2: Сокращенное название организации
A4: Амортизация основных фондов и ее использование в отчетном году
F6: (тыс. руб.)
A7: Наименование показателей | B7: Всего основные фонды | C7: В т.ч. фонды основного вида деятельности | D7: Из них
D8: здания | E8: сооружения | F8: машины и оборудование
A9: 1 | B9: 2 | C9: 3 | D9: 4 | E9: 5 | F9: 6
A10: 1. Остаток средств амортизационного фонда на начало года
A11: 2. Сумма начисленной за год амортизации, включенной в себестоимость продукции
A12: 3. Использовано за отчетный год средств для приобретения и создания основных фондов, предназначенных для собственного использования:
A13: 3.1. Амортизационных средств
A14: 3.2. Других собственных средств, кроме амортизации
A15: 3.3. Привлеченных средств
A16: 4. Основные фонды (балансовая стоимость на конец года), по которым амортизация не начисляется, всего
A17: из них:
A18: 4.1. Полностью амортизированные (изношенные) на конец года
B20: Подпись
C21: должность, Ф.И.О. исполнителя и его контактный телефон

Sheet Раздел VIII
B9: VIII. ВНЕШНЕЭКОНОМИЧЕСКАЯ ДЕЯТЕЛЬНОСТЬ

Sheet VIII-1
M1: Таблица VIII/1
A2: Сокращенное название организации
A4: Контракты и соглашения по внешне-техническому сотрудничеству с зарубежными странами
A6: № п/п | B6: Наименование контракта, соглашения, договора и др. | C6: Срок действия | E6: Страна | F6: Наименование партнера (фирмы) | G6: Краткое содержание контракта | H6: Объем экспорта продукции | K6: Объем импорта продукции
C7: начало | D7: окончание | H7: валюта | I7: всего по контракту | J7: за отчетный год | K7: валюта | L7: всего по контракту | M7: за отчетный год
A8: 1 | B8: 2 | C8: 3 | D8: 4 | E8: 5 | F8: 6 | G8: 7 | H8: 8 | I8: 9 | J8: 10 | K8: 11 | L8: 12 | M8: 13
A9: 1
A10: =A9+1 -> 2
H12: Подпись
I13: должность, Ф.И.О. исполнителя и его контактный телефон

Sheet VIII-2
H1: Таблица VIII/2
B2: Сокращенное название предприятия
A4: Общие объемы экспорта продукции и услуг организции
A6: Код строки | B6: Наименование показателя | C6: Объемы производства | F6: Объем поставок
C7: валюта | D7: за отчетный год | E7: за предыдущий отчетному год | F7: валюта | G7: за отчетный год | H7: за предыдущий отчетному год
A8: 1 | B8: 2 | C8: 3 | D8: 4 | E8: 5 | F8: 6 | G8: 7 | H8: 8
A9: 100 | B9: Поставлено на экспорт всего:
A10: 101 | B10: в том числе продукции военного назначения
A11: 102 | B11: Экспорт в страны СНГ
A12: 103 | B12: в том числе продукции военного назначения
A13: 104 | B13: Экспорт в прочие страны
A14: 105 | B14: в том числе продукции военного назначения
D16: Подпись
E17: должность, Ф.И.О. исполнителя и его контактный телефон

Sheet VIII-3
G1: Таблица VIII/3
B2: Сокращенное название организации
A4: Продукция гражданского назначения поставляемая на экспорт
A6: № п/п | B6: Наименование продукции | C6: Код ОКПД 2 | D6: Наименование страны-покупателя | E6: Объем экспорта
E7: валюта | F7: за отчетный год | G7: за предыдущий отчетному год
A8: 1 | B8: 2 | C8: 3 | D8: 4 | E8: 5 | F8: 6 | G8: 7
D12: Подпись
E13: должность, Ф.И.О. исполнителя и его контактный телефон

Sheet VIII-4
E1: Таблица VIII/4
A2: Сокращенное название организации
B4: Общие объемы импорта продукции
A6: Код строки | B6: Наименование показателя | C6: Объем импорта
C7: валюта | D7: за отчетный год | E7: за предыдущий отчетному год
A8: 1 | B8: 2 | C8: 3 | D8: 4 | E8: 5
A9: 100 | B9: Приобретено продукции иностранного производства, всего
A10: 101 | B10: в том числе: на внутреннем рынке
A11: 110 | B11: Приобретено продукции производства стран СНГ, всего
A12: 111 | B12: в том числе: приобретено на внутреннем рынке
A13: 120 | B13: Приобретено продукции производства прочих стран, всего
A14: 121 | B14: в том числе: приобретено на внутреннем рынке
C16: Подпись
D17: должность, Ф.И.О. исполнителя и его контактный телефон

Sheet VIII-5
G1: Таблица VIII/5
A2: Сокращенное название организации
A4: Сведения об импортируемой продукции
A6: № п/п | B6: Наименование продукции | C6: Наименование страны-производителя | D6: Наименование фирмы-производителя | E6: Объем импорта
E7: валюта | F7: за отчетный год | G7: за предыдущий отчетному год
A8: 1 | B8: 2 | C8: 3 | D8: 4 | E8: 5 | F8: 6 | G8: 7
C12: Подпись
D13: должность, Ф.И.О. исполнителя и его контактный телефон

Sheet раздел IX
B9: IX. ОБЪЕКТЫ НЕДВИЖИМОСТИ И ЗЕМЕЛЬНЫЕ УЧАСТКИ

Sheet IX-1
J1: Таблица IX/1
B2: Сокращенное название организации
A4: Сводные сведения об объектах недвижимости
A6: Код строки | B6: Категория | C6: Общее количество объектов, шт. | D6: Общая площадь, м2 | E6: Зарегистрировано право собственности в отчетном году | G6: Продано, за отчетный год | I6: Списано (снесено) за отчетный год | K6: Внесено в Уставной капитал других организаций в отчетном году | M6: Сдано в аренду в отчетном году | O6: Получено в аренду в отчетном году | Q6: Доход от сдачи объектов основных средств в аренду, тыс.руб. | R6: Выручка от продажи объектов основных средств и иных внеоборотных активов, тыс.руб. | S6: Примечания
E8: количество объектов, шт. | F8: площадь, м2 | G8: количество объектов, шт. | H8: площадь, м2 | I8: количество объектов, шт. | J8: площадь, м2 | K8: количество объектов, шт. | L8: площадь, м2 | M8: количество объектов, шт. | N8: площадь, м2 | O8: количество объектов, шт. | P8: площадь, м2
A9: 1 | B9: 2 | C9: 3 | D9: 4 | E9: 5 | F9: 6 | G9: 7 | H9: 8 | I9: 9 | J9: 10 | K9: 11 | L9: 12 | M9: 13 | N9: 14 | O9: 15 | P9: 16 | Q9: 17 | R9: 18 | S9: 19
A10: 100 | B10: Земельные участки
A11: 200 | B11: Здания, в т.ч.:
A12: 210 | B12: производственные
A13: 220 | B13: административные
A14: 230 | B14: имущественных комплексов социального назначения
A15: 240 | B15: прочие
A16: 300 | B16: Сооружения
A17: 400 | B17: Объекты незавершенного строительства | K17: Х | L17: Х | M17: Х | N17: Х | O17: Х | P17: Х | Q17: Х | R17: Х
A18: 500 | B18: Прочие объекты недвижимости
A19: 600 | B19: Производственные площади, в т.ч. | C19: X | E19: X | G19: X | I19: X | K19: X | M19: X | O19: X | Q19: X | R19: X
A20: 610 | B20: используемых для выполнения ГОЗ и ВТС | C20: X | E20: X | G20: X | I20: X | K20: X | M20: X | O20: X | Q20: X | R20: X
P23: Подпись
Q24: должность, Ф.И.О. исполнителя и его контактный телефон

Sheet IX-2
A1: VIII-1 | N1: Таблица IX/2
B2: Сокращенное название организации
A4: Сведения о земельных участках
A6: № п/п | B6: Наименование | C6: Адрес участка | D6: Кадастровый номер | E6: Площадь, м2 | F6: Правоустанавливающий/правоудостоверяющий документ | L6: Стоимость выкупа, руб./м2 | M6: Обременения | N6: Примечание
F7: собственник | G7: вид документа | H7: дата | I7: номер | J7: срок действия | K7: ставка, руб./м2
A8: 1 | B8: 2 | C8: 3 | D8: 4 | E8: 5 | F8: 6 | G8: 7 | H8: 8 | I8: 9 | J8: 10 | K8: 11 | L8: 12 | M8: 13 | N8: 14
A9: 1. Земельные участки вошедшие в уставный капитал
A10: 1 | B10: 2 | C10: 3 | D10: 4 | E10: 5 | G10: 6 | H10: 7 | I10: 8 | J10: 9 | K10: 10 | L10: 11 | M10: 12 | N10: 13
A13: 2. Земельные участки не вошедшие в уставный капитал
A14: 1 | B14: 2 | C14: 3 | D14: 4 | E14: 5 | F14: 6 | G14: 7 | H14: 8 | I14: 9 | J14: 10 | K14: 11 | L14: 12 | M14: 13 | N14: 14
I18: Подпись
J19: должность, Ф.И.О. исполнителя и его контактный телефон

Sheet IX-3
O1: Таблица IX/3
B2: Сокращенное название организации
A4: Общие сведения о зданиях и сооружениях, находящихся на балансе организации
A6: № п/п | B6: Наименование объекта | C6: Адрес объекта | D6: Кадастровый номер | E6: Номер техническо-го паспорта БТИ и дата | F6: Площадь застройки, м2 | G6: Общая площадь объекта, м2 | H6: Зарегистри-ровано право соб-ственности, м2 | I6: Свидетельство о регистрации | K6: Свободные площади, м2 | M6: Остаточная балансовая ст-ть, тыс.руб. (без НДС) | N6: Обременения | O6: Примечание
I7: дата | J7: номер | K7: всего | L7: в т.ч. сданы в аренду
A8: 1 | B8: 2 | C8: 3 | D8: 4 | E8: 5 | F8: 6 | G8: 7 | H8: 8 | I8: 9 | J8: 10 | K8: 11 | L8: 12 | M8: 13 | N8: 14 | O8: 15
A9: 1. Объекты недвижимости, вошедшие в уставный капитал (фонды)
A10: 1 | B10: 2 | C10: 3 | D10: 4 | E10: 5 | F10: 6 | G10: 7 | H10: 8 | I10: 9 | J10: 10 | K10: 11 | L10: 12 | M10: 13 | N10: 14 | O10: 15
A13: 2. Новое строительство
A16: 3. Объекты недвижимости, находящиеся на балансе, но не вошедшие в уставный капитал (фонды)
I20: Подпись
J21: должность, Ф.И.О. исполнителя и его контактный телефон

Sheet IX-4
S1: Таблица IХ/4
B2: Сокращенное название организации
A4: Технические характеристики объектов недвижимости
A6: № п/п | B6: Наименование объекта | C6: Год ввода в эксплу-атацию | D6: Этаж-ность | E6: % износа объекта | F6: Материал конструктивных элементов / фактический % износа | K6: Фактический % износа
F7: фундаменты | G7: стены | H7: перекрытия | I7: крыша | J7: благоустройство | K7: отопление | L7: горячее водоснабжение | M7: холодное водоснабжение | N7: пожарный водопровод | O7: вентиляция | P7: канализация | Q7: энергоснабжение | R7: газооборудование | S7: лифты
A8: 1 | B8: 2 | C8: 3 | D8: 4 | E8: 5 | F8: 6 | G8: 7 | H8: 8 | I8: 9 | J8: 10 | K8: 11 | L8: 12 | M8: 13 | N8: 14 | O8: 15 | P8: 16 | Q8: 17 | R8: 18 | S8: 19
A9: 1. Объекты недвижимости, вошедшие в уставный капитал (фонд)
A10: 1.1
A11: …
A12: 2. Новое строительство
A13: 2.1
A14: …
A15: 3. Объекты недвижимости, находящиеся на балансе, но не вошедшие в уставный капитал (фонд)
A16: 3.1
A17: …
J19: Подпись
K20: Должность, Ф.И.О. исполнителя и его контактный телефон

Sheet IX-5
I1: Таблица IX/5
B2: Сокращенное название организации
A4: Сведения об объектах социальной сферы, находящихся на балансе организации
A6: № п/п | B6: Наименование объекта | C6: Назначение объекта | D6: Вид использования | E6: Расходы на содержание объекта, тыс.руб. | G6: Выручка от использования объекта, тыс.руб. | I6: Примечание
E7: отчетный год | F7: предыдущий год | G7: отчетный год | H7: предыдущий год
A8: 1 | B8: 2 | C8: 3 | D8: 4 | E8: 5 | F8: 6 | G8: 7 | H8: 8 | I8: 9
A9: 1. Объекты недвижимости, вошедшие в уставный капитал (фонд)
A12: 2. Новое строительство
A15: 3. Объекты недвижимости, находящиеся на балансе, но не вошедшие в уставный капитал (фонд)
E19: Подпись
F20: должность, Ф.И.О. исполнителя и его контактный телефон

Sheet IX-6
J1: Таблица IX/6
B2: Сокращенное название организации
A4: Сведения об объектах незавершенного строительства
A6: № п/п | B6: Наименование объекта | C6: Наименование (назначение) объекта | D6: Год начала строительства | E6: Год ввода в эксплуатацию (по проекту) | F6: Процент готовности | G6: Сметная стоимость | I6: Фактические затраты, тыс.руб. | J6: Примечание
G7: в ценах (год) | H7: всего, тыс. руб
A8: 1 | B8: 2 | C8: 3 | D8: 4 | E8: 5 | F8: 6 | G8: 7 | H8: 8 | I8: 9 | J8: 10
A12: ИТОГО:
F14: Подпись
G15: должность, Ф.И.О. исполнителя и его контактный телефон

Sheet IX-7
N1: Таблица IX/7
A2: Сокращенное название организации
A4: Сведения о сдаче в аренду объектов недвижимости в отчетном году
A6: № п/п | B6: Наименование объекта | C6: Общая площадь объекта, кв.м | D6: Свободные площади, кв.м | E6: В т.ч. аренда | I6: Выручка от сдачи в аренду, тыс.руб. (с НДС) | K6: Договор аренды | N6: Арендатор/ Собственник
E7: площадь, кв.м | F7: занимаемые помещения | G7: назначение арендуемых площадей | H7: арендная ставка, руб./кв.м/год (с НДС) | I7: начисление по аренде недвижимости | J7: прочие начисления арендатору | K7: дата | L7: номер | M7: срок действия
A8: 1 | B8: 2 | C8: 3 | D8: 4 | E8: 5 | F8: 6 | G8: 7 | H8: 8 | I8: 9 | J8: 10 | K8: 11 | L8: 12 | M8: 13 | N8: 14
A11: ИТОГО: | F11: - | K11: -
I14: Подпись
J15: должность, Ф.И.О. исполнителя и его контактный телефон

Sheet IX-8
I1: Таблица IX/8
A2: Сокращенное название организации
B4: Сведения об объектах недвижимости, переданных в залог или обремененных иным образом (за исключением аренды)
A6: № п/п | B6: Наименование объекта | C6: Наименование организаций-кредиторов | D6: Причины обременения | E6: Документ | H6: Сроки обременения | I6: Сумма обязательств (кредитов, займов, исков и т.д.)
E7: вид документа | F7: дата | G7: номер
A8: 1 | B8: 2 | C8: 3 | D8: 4 | E8: 5 | F8: 6 | G8: 7 | H8: 8 | I8: 9
A11: ИТОГО: | E11: -
F13: Подпись
G14: должность, Ф.И.О. исполнителя и его контактный телефон

Sheet IX-9
O1: Таблица IX/9
A2: Сокращенное название организации
B5: Сведения об объектах недвижимости, отчужденных в отчетном году и планируемых к отчуждению в следующем за отчетным годом
A7: № п/п | B7: Наименование объекта | C7: Адрес объекта | D7: Кадастровый номер | E7: Год ввода в эксплу-атацию | F7: Общая площадь объекта, кв.м | G7: Способ отчуж-дения | H7: Документ-основание | K7: Дата реали-зации | L7: Новый собственник | M7: Стоимость объекта в тыс.руб. | O7: Цена продажи, руб.с НДС
H8: вид документа | I8: дата | J8: номер | M8: остаточная баланс. без НДС | N8: оце-ночная с НДС
A9: 1 | B9: 2 | C9: 3 | D9: 4 | E9: 5 | F9: 6 | G9: 7 | H9: 8 | I9: 9 | J9: 10 | K9: 11 | L9: 12 | M9: 13 | N9: 14 | O9: 15
A10: 1. Отчужденные объекты недвижимости
A11: 1.1
A12: 1.2
A13: …
A14: ИТОГО по разделу 1: | G14: - | N14: -
A15: 2. Планируемые к отчуждению объекты недвижимости
A16: 2.1 | H16: -
A17: 2.2 | H17: -
A18: … | H18: -
A19: ИТОГО по разделу 2: | G19: - | N19: -
J21: Подпись
K22: должность, Ф.И.О. исполнителя и его контактный телефон

Sheet IX-10
M1: Таблица IX/10
A2: Сокращенное название организации
B5: Сведения о снесенных (ликвидированных) объектах недвижимости в отчетном году и планируемых к сносу в следующем за отчетным годом
A7: № п/п | B7: Наименование объекта | C7: Адрес объекта | D7: Кадастровый номер | E7: Год ввода в эксплу-атацию | F7: Балансовая стоимость на дату списания, тыс.руб. | G7: Общая площадь объекта, кв.м | H7: Причина сноса (ликвидации) | I7: Дата сноса (ликвидации) | J7: Подтверждающий документ | M7: Примечание
J8: вид документа | K8: дата | L8: номер
A9: 1 | B9: 2 | C9: 3 | D9: 4 | E9: 5 | F9: 6 | G9: 7 | H9: 8 | I9: 9 | J9: 10 | K9: 11 | L9: 12 | M9: 13
A10: 1. Снесенные (ликвидированные) объекты недвижимости
A11: 1.1
A12: 1.2
A13: …
A14: ИТОГО по разделу 1: | D14: - | H14: -
A15: 2. Планируемые к сносу
A16: 2.1
A17: 2.2
A18: …
A19: ИТОГО по разделу 2: | D19: - | H19: -
H21: Подпись
I22: должность, Ф.И.О. исполнителя и его контактный телефон

Sheet IX-11
L1: Таблица IX/11
A2: Сокращенное название организации
A4: Сведения о поступлении денежных средств от использования объектов недвижимости
L6: (в тыс.руб. без НДС)
A7: № п/п | B7: Наименование показателя | C7: 1 кв. | E7: 2 кв. | G7: 3 кв. | I7: 4 кв. | K7: 201__ год.
C8: план | D8: факт | E8: план | F8: факт | G8: план | H8: факт | I8: план | J8: факт | K8: план | L8: факт
A9: 1 | B9: 2 | C9: 3 | D9: 4 | E9: 5 | F9: 6 | G9: 7 | H9: 8 | I9: 9 | J9: 10 | K9: 11 | L9: 12
A10: 1 | B10: Доход от сдачи объектов основных средств (только объектов недвижимости) и иных внеоборотных активов в аренду всего, в т.ч.
B11: здания (сооружения), земельные участки, в т.ч.
B12: • здания:
B13: производственные
B14: административные
B15: складские
B16: имущественных комплексов социального назначения (пансионаты, объекты, здравоохранения, учреждения детского досуга и т.п.)
B17: • земельные участки
A18: 2 | B18: Выручка от продажи объектов основных средств и иных внеоборотных активов, в т.ч.
B19: • здания:
B20: производственные
B21: административные
B22: складские
B23: имущественных комплексов социального назначения (пансионаты, объекты, здравоохранения, учреждения детского досуга и т.п.)
B24: • земельные участки
F26: Подпись
G27: должность, Ф.И.О. исполнителя и его контактный телефон

Sheet раздел X
B9: X. ИНТЕЛЛЕКТУАЛЬНАЯ СОБСТВЕННОСТЬ И НЕМАТЕРИАЛЬНЫЕ АКТИВЫ

Sheet X-1
A1: X-1 | N1: Таблица X/1
B2: Сокращенное название организации
A4: Сведения о полученных охранных документах и поданных заявках на объекты интеллектуальной собственности в отчетном году
A6: № п/п | B6: Вид ОИС | C6: Код ОКОФ | D6: Наименование ОИС | E6: Ожидаемый целевой результат применения | F6: Правооблада- тель | G6: Страна патентования и сфера действия | H6: Реквизиты охранного документа | K6: Реквизиты заявки на выдачу охранного документа | N6: Примечание
H7: вид | I7: номер | J7: дата регистрации в Госреестре | K7: заявитель | L7: номер заявки | M7: дата приори-тета
A8: 1 | B8: 2 | C8: 3 | D8: 4 | E8: 5 | F8: 6 | G8: 7 | H8: 8 | I8: 9 | J8: 10 | K8: 11 | L8: 12 | M8: 13 | N8: 14
I12: Подпись
J13: должность, Ф.И.О. исполнителя и его контактный телефон

Sheet Х-2
L1: Таблица X/2
B2: Сокращенное название организации
A4: Введение объектов интеллектуальной собственности (ОИС) в хозяйственный и гражданско-правовой оборот
A6: № п/п | B6: Вид ОИС | C6: Код ОКОФ | D6: Вид, номер охранного документа | E6: Наименование ОИС | F6: Правооблада- тель | G6: Характер введения ОИС в хозяйственный или гражданско-правовой оборот (подтверждающий документ, его номер, дата) | K6: Постановка на учет в качестве НМА
G7: собственное производство | H7: продажа лицензии | I7: уступка охранного документа | J7: покупка лицензии | K7: дата | L7: инвентарный номер
A8: 1 | B8: 2 | C8: 3 | D8: 4 | E8: 5 | F8: 6 | G8: 7 | H8: 8 | I8: 9 | J8: 10 | K8: 11 | L8: 12
H12: Подпись
I13: должность, Ф.И.О. исполнителя и его контактный телефон

Sheet X-3
H1: Таблица X/3
B2: Сокращенное название организации
A4: Сведения об использовании введенных в отчетном году ОИС в собственном производстве
A6: № п/п | B6: Объект НМА | C6: Инвентарный номер | D6: Использование в производстве продукции | G6: Достигнутые качественные результаты использования ОИС в собственном производстве | H6: Расчетный годовой экономический эффект, тыс. руб.
D7: наименование продукции | E7: ЕКПС | F7: ОКПД2
A8: 1 | B8: 2 | C8: 3 | D8: 4 | E8: 5 | F8: 6 | G8: 7 | H8: 8
E13: Подпись
F14: должность, Ф.И.О. исполнителя и его контактный телефон

Sheet X-4
I1: Таблица X/4
B2: Сокращенное название организации
B4: Сведения об учтенных в составе нематериальных активов объектах интеллектуальной собственности по состоянию на конец отчетного года
I5: (тыс.руб.)
A6: № п/п | B6: Объект НМА | C6: Инвентарный номер | D6: Срок полезного использования | F6: Стоимость объекта НМА | I6: Начисленная амортизация
D7: начало | E7: окончание | F7: первона-чальная | G7: дата переоценки | H7: текущая рыночная
A8: 1 | B8: 2 | C8: 3 | D8: 4 | E8: 5 | F8: 6 | G8: 7 | H8: 8 | I8: 9
A11: Объекты НМА, полученные от государственных заказчиков
D14: Подпись
E15: должность, Ф.И.О. исполнителя и его контактный телефон

Sheet X-5
H1: Таблица X/5
B2: Сокращенное название организации
A4: Финансовые результаты процессов коммерциализации объектов интеллектуальной собственности и трансфера технологий (внутренний рынок)
A6: Код строки | B6: Виды процессов коммерциализации ОИС | C6: Поступления (тыс. руб.) | F6: Выплаты (тыс. руб.)
C7: всего | D7: паушаль- ные платежи | E7: роялти | F7: всего | G7: паушаль- ные платежи | H7: роялти
A8: 1 | B8: 2 | C8: 3 | D8: 4 | E8: 5 | F8: 6 | G8: 7 | H8: 8
A9: 100 | B9: Продажа/покупка ОИС, в том числе:
A10: 101 | B10: патентов на изобретения
A11: 102 | B11: беспатентных изобретений
A12: 103 | B12: патентов на полезные модели
A13: 104 | B13: патентов на промышленные образцы
A14: 105 | B14: секретов производства (ноу-хау)
A15: 106 | B15: средств индивидуализации
A16: 107 | B16: программных продуктов
A17: 108 | B17: единых технологий
A18: 109 | B18: результатов НИОКР и технологических разработок
A19: 200 | B19: Сопутствующие продажам ОИС работы и услуги (инжиниринг, аутсорсинг и пр.)
A20: 210 | B20: Продажа/покупка патентных лицензий
... A27: 300 | B27: Всего по видам коммерциализации
B29: Подпись
C30: должность, Ф.И.О. исполнителя и его контактный телефон

Sheet X-6
A1: X-2 | H1: Таблица X/6
B2: Сокращенное название организации
A4: Финансовые результаты процессов коммерциализации объектов интеллектуальной собственности и трансфера технологий (экспорт-импорт)
A6: Код строки | B6: Виды процессов коммерциализации ОИС | C6: Поступления (тыс.долл. США) | F6: Выплаты (тыс.долл. США)
C7: всего | D7: паушаль- ные платежи | E7: роялти | F7: всего | G7: паушаль- ные платежи | H7: роялти
A8: 1 | B8: 2 | C8: 3 | D8: 4 | E8: 5 | F8: 6 | G8: 7 | H8: 8
A9: 100 | B9: Продажа/покупка ОИС, в том числе:
A10: 101 | B10: патентов на изобретения
A11: 102 | B11: беспатентных изобретений
A12: 103 | B12: патентов на полезные модели
A13: 104 | B13: патентов на промышленные образцы
A14: 105 | B14: секретов производства (ноу-хау)
A15: 106 | B15: средств индивидуализации
A16: 107 | B16: программных продуктов
A17: 108 | B17: единых технологий
A18: 109 | B18: результатов НИОКР и технологических разработок
A19: 200 | B19: Сопутствующие продажам ОИС работы и услуги (инжиниринг, аутсорсинг и пр.)
A20: 210 | B20: Продажа/покупка патентных лицензий
... A28: 300 | B28: Всего по видам коммерциализации
C30: Подпись
D31: должность, Ф.И.О. исполнителя и его контактный телефон

Sheet раздел XI
B9: ХI. ПЕРСОНАЛ ОРГАНИЗАЦИИ

Sheet XI-1
L1: Таблица XI/1
B2: Сокращенное название организации
A4: Структура численности персонала и оплата труда
A6: Код строки | B6: Показатели | C6: Численность всего, чел. | D6: По возрастному составу, чел.: | J6: Среднемесяч- ная заработная плата, тыс. руб. | K6: Фонд заработной платы, начисленной работникам списочного состава (без совместителей и работников несписочного состава), тыс. руб. | L6: Примечание
D7: до 30 лет | E7: от 30 до 35 лет | F7: от 35 до 40 лет | G7: от 40 до 50 лет | H7: от 50 до 60 лет | I7: от 60 лет и выше
A8: 1 | B8: 2 | C8: 3 | D8: 4 | E8: 5 | F8: 6 | G8: 7 | H8: 8 | I8: 9 | J8: 10 | K8: 11 | L8: 12
A9: 1000 | B9: ВСЕ РАБОТНИКИ (среднесписочная численность без совместителей и работников несписочного состава), в том числе:
A10: 1100 | B10: ПРОМЫШЛЕННО-ПРОИЗВОДСТВЕННЫЕ РАБОТНИКИ:
A11: 1110 | B11: Рабочие, в т.ч.:
A12: 1111 | B12: рабочие со средним профессиональным образованием
A13: 1120 | B13: Инженеры, технические работники, разработчики и специалисты, в т.ч.:
A14: 1121 | B14: специалисты среднего уровня квалификации
A15: 1122 | B15: специалисты высшего уровня квалификации
A16: 1130 | B16: Вспомогательные и обслуживающие производственную деятельность работники, в т.ч.:
A17: 1131 | B17: рабочие со средним профессиональным образованием
A18: 1200 | B18: АДМИНИСТРАТИВНО-УПРАВЛЕНЧЕСКИЕ РАБОТНИКИ, в т.ч.:
A19: 1201 | B19: Руководители
A20: 1202 | B20: Административный персонал
... A22: 1300 | B22: НЕПРОМЫШЛЕННЫЙ ПЕРСОНАЛ
A23: 1400 | B23: Численность работников, занятых в производстве РКТ, в т.ч. | J23: Х | K23: Х
A24: 1410 | B24: рабочие
A25: 1420 | B25: административно-управленческий персонал
A26: 1500 | B26: Численность работников, занятых в производстве гражданской продукции, в т.ч.
A27: 1510 | B27: рабочие
A28: 1520 | B28: административно-управленческий персонал
A29: 2000 | B29: Принято работников, в т.ч.: | J29: Х | K29: Х
A30: 2010 | B30: промышленно-производственных, в т.ч.: | J30: Х | K30: Х
A31: 2011 | B31: рабочих | J31: Х | K31: Х
A32: 2012 | B32: инженеров, технических работников, разработчиков и специалистов | J32: Х | K32: Х
A33: 2020 | B33: административно-управленческих работников | J33: Х | K33: Х
A34: 2030 | B34: непромышленного персонала | J34: Х | K34: Х
A35: 2100 | B35: В рамках договора целевого обучения, в т.ч. | J35: Х | K35: Х
A36: 2101 | B36: из вузов | J36: Х | K36: Х
A37: 2102 | B37: из образовательных учреждений среднего профессионального образования | J37: Х | K37: Х
A38: 2200 | B38: По направлению службы занятости | J38: Х | K38: Х
A39: 2300 | B39: По заявке рекрутинговым агентством | J39: Х | K39: Х
A40: 2400 | B40: Через портал «Работа в России» | J40: Х | K40: Х
... A50: 4000 | B50: Численность работников, имеющих ученую степень | J50: Х | K50: Х
I53: Подпись
J54: должность, Ф.И.О. исполнителя и его контактный телефон

Sheet XI-2
J1: Таблица XI/2
B2: Сокращенное название организации
B4: Справка-объективка на руководящий состав организации
A6: № п/п | B6: Фамилия, имя, отчество | C6: Дата рождения | D6: Гражданство | E6: Наличие образования по специальности «Управленческая деятельность и менеджмент» (Да/Нет) | F6: Образование | J6: Является ли народным депутатом | K6: Повышение квалификации и профессиональной переподготовки | O6: Владение иностранными языками | Q6: Ученая степень, ученое звание | T6: Трудовая деятельность
F7: наименование учебного заведения | G7: специальность и квалификация | H7: начало обучения | I7: окончание обучения | K7: наименование учебного заведения | L7: специаль- ность и квалификация | M7: начало обучения | N7: окончание обучения | O7: наименова-ние иностран-ного языка | P7: степень владения | Q7: наимено- вание | R7: область науки | S7: год присвоения | T7: дата поступления | U7: дата увольнения | V7: должность, место работы (службы, учебы)
A8: 1 | B8: 2 | C8: 3 | D8: 4 | E8: 5 | F8: 6 | G8: 7 | H8: 8 | I8: 9 | J8: 10 | K8: 11 | L8: 12 | M8: 13 | N8: 14 | O8: 15 | P8: 16 | Q8: 17 | R8: 18 | S8: 19 | T8: 20 | U8: 21 | V8: 22
Q12: Подпись
R13: должность, Ф.И.О. исполнителя и его контактный телефон

Sheet XI-3
F1: Таблица ХI/3
B2: Сокращенное название организации
A4: Сведения о повышении квалификации и переподготовке руководителей и служащих
F5: (чел.)
A6: Код строки | B6: Показатель | C6: Обучено за отчетный год
C7: всего | D7: руководителей | E7: специалистов | F7: др. служащих
A8: 1 | B8: 2 | C8: 3 | D8: 4 | E8: 5 | F8: 6
A9: 100 | B9: Повысили квалификацию (срок освоения программы не менее 16 часов), всего, в т.ч.:
A10: 110 | B10: в образовательных организациях высшего образования
A11: 120 | B11: в организациях дополнительного профессионального образования
A12: 200 | B12: Прошли профессиональную переподготовку (срок освоения программы не менее 250 часов), всего, в т.ч.:
A13: 210 | B13: в образовательных организациях высшего образования по программам профессиональной переподготовки, реализуемых или разработанных в рамках основных образовательных программ
A14: 220 | B14: в образовательных организациях высшего образования по иным программам профессиональной переподготовки
A15: 230 | B15: в организация дополнительного профессионального образования
A16: 300 | B16: Прошли обучение: | C16: Х | D16: Х | E16: Х | F16: Х
A17: 310 | B17: в связи с созданием нового производства
A18: 320 | B18: в связи с высвобождением
A19: 330 | B19: за рубежом
A20: 340 | B20: работники в возрасте до 35 лет
A22: Сумма средств, затраченных на повышение квалификации и профессиональную переподготовку руководителей и служащих | E22: тыс.руб.
C24: Подпись
D25: должность, Ф.И.О. исполнителя и его контактный телефон

Sheet ХI-4
K1: Таблица ХI/4
B2: Сокращенное название организации
A4: Список работников, планируемых для выдвижения на должности генерального директора, его заместителей и главного бухгалтера
A6: № п/п | B6: Должность для замещения | C6: Фамилия, имя, отчество рекомен-дуемого в резерв | D6: Дата рождения | E6: Занимаемая должность | F6: Сведения об опыте работы на основных должностях | G6: Образование, что окончил, когда, специальность | H6: Данные о повышении квалификации | I6: Дата зачисления в кадровый резерв | J6: Выводы и рекомендации по последней аттестации | K6: Примечание
A7: 1 | B7: 2 | C7: 3 | D7: 4 | E7: 5 | F7: 6 | G7: 7 | H7: 8 | I7: 9 | J7: 10 | K7: 11
G11: Подпись
H12: должность, Ф.И.О. исполнителя и его контактный телефон

Sheet XI-5
A1: XI-5 | C1: Таблица ХI/5
A2: Сокращенное название организации
A4: Сведения о профессиональном обучении рабочих
A6: Код строки | B6: Показатель | C6: Количество рабочих, чел.
A7: 1 | B7: 2 | C7: 3
A8: 100 | B8: Прошли профессиональную подготовку всего, в т.ч.:
A9: 110 | B9: обучено впервые, из них
A10: 111 | B10: по программам профессионального обучения
A11: 112 | B11: по программам квалифицированных рабочих и служащих в рамках СПО
A12: 120 | B12: обучено вторым (совмещенным) профессиям, из них
A13: 121 | B13: по программам профессионального обучения
A14: 122 | B14: по программам квалифицированных рабочих и служащих в рамках СПО
A15: 130 | B15: переподготовлено
A16: 200 | B16: Повысили квалификацию всего, в т.ч.:
A17: 210 | B17: на производственно-экономических курсах
A18: 220 | B18: на курсах целевого назначения
A19: 230 | B19: на прочих курсах
... A24: 330 | B24: работников в возрасте до 35 лет
A26: Сумма средств, затраченных на повышение квалификации и переподготовку рабочих
C27: тыс. руб.
B29: Подпись
C30: должность, Ф.И.О. исполнителя и его контактный телефон

Sheet XI-6
J1: Таблица ХI/6
B2: Сокращенное название организации
A4: Востребованность должностей и специальностей персонала организации в части персонала со средним профессиональным образованием по состоянию на конец отчетного периода
A6: № п/п | B6: Должность, профессия | D6: Специальность среднего профессионального образования | F6: Численность | G6: Потребность | H6: Удельный вес к общей численности | J6: Примечание
B7: наименование | C7: код по ОКПДТР | D7: наименование | E7: код по ОКСО | H7: текущий | I7: необходимый
A8: 1 | B8: 2 | C8: 3 | D8: 4 | E8: 5 | F8: 6 | G8: 7 | H8: 8 | I8: 9 | J8: 10
F14: Подпись
G15: должность, Ф.И.О. исполнителя и его контактный телефон

Sheet XI-7
J1: Таблица ХI/7
B2: Сокращенное название организации
A4: Востребованность должностей и специальностей персонала организации в части специалистов с высшим образованием по состоянию на конец отчетного периода
A6: № п/п | B6: Должность, профессия | D6: Специальность высшего образования | F6: Численность работников | G6: Потребность | H6: Удельный вес к общей численности | J6: Примечание
B7: наименование | C7: код по ОКПДТР | D7: наименование | E7: код по ОКСО | H7: текущий | I7: необходимый
A8: 1 | B8: 2 | C8: 3 | D8: 4 | E8: 5 | F8: 6 | G8: 7 | H8: 8 | I8: 9 | J8: 10
F14: Подпись
G15: должность, Ф.И.О. исполнителя и его контактный телефон

Sheet XI-8
E1: Таблица XI/8
B2: Сокращенное название организации
A4: Сведения об условиях труда
A6: Код строки | B6: Показатели | C6: Ед. измер. | D6: Отчетный год | E6: Предыдущий отчетному год
A8: 1 | B8: 2 | C8: 3 | D8: 4 | E8: 5
A9: 1. Расходы на объекты социальной инфраструктуры
A10: 100 | B10: Расходы на объекты социальной инфраструктуры (всего), в том числе: | C10: тыс.руб.
A11: 101 | B11: Здравпункты и медучреждения | C11: тыс.руб.
A12: 102 | B12: Профилактории, пансионаты матери и ребенка | C12: тыс.руб.
A13: 103 | B13: Общежития и гостиницы | C13: тыс.руб.
A14: 104 | B14: Объекты общественного питания | C14: тыс.руб.
A15: 105 | B15: Объекты бытового обслуживания и торговли | C15: тыс.руб.
A16: 106 | B16: Турбазы и спорткомплексы | C16: тыс.руб.
A17: 107 | B17: Культурно-просветительные учреждения | C17: тыс.руб.
A18: 108 | B18: Дошкольные учреждения | C18: тыс.руб.
A19: 109 | B19: Объекты ЖКХ | C19: тыс.руб.
A20: 110 | B20: Другие | C20: тыс.руб.
A21: 2. Сведения об эффективности охраны труда
A22: 200 | B22: Количество несчастных случаев на производстве | C22: случ.
A23: 300 | B23: Количество больных с профессиональным заболеванием, всего | C23: человек
A24: 310 | B24: Количество человеко-дней временной нетрудоспособности, вызванной несчастными случаями на производстве | C24: чел.-дн.
A25: 320 | B25: Количество человеко-дней временной нетрудоспособности, вызванной профессиональным заболеванием | C25: чел.-дн.
A26: 400 | B26: Сумма выплат, вызванных несчастным случаем на производстве | C26: тыс.руб.
A27: 410 | B27: Сумма выплат по временной нетрудоспособности, вызванной профессиональным заболеванием | C27: тыс.руб.
A28: 500 | B28: Количество случаев общим заболеванием, всего | C28: случ.
A29: 600 | B29: Количество человеко-дней временной нетрудоспособности, вызванной общим заболеванием | C29: чел.-дн.
A30: 700 | B30: Сумма выплат по временной нетрудоспособности, вызванной общим заболеванием | C30: тыс.руб.
B32: Подпись
C33: должность, Ф.И.О. исполнителя и его контактный телефон

Sheet ХI-9
F1: Таблица ХI/9
A2: Сокращенное наименование организации
A4: Cписок работников организации, имеющих ученую степень кандидата (доктора) наук
A7: № п/п | B7: Фамилия, имя, отчество | C7: Дата рождения | D7: Должность | E7: Ученая степень, год присвоения | F7: Ученое звание (указать отрасль науки и вуз)
A8: 1 | B8: 2 | C8: 3 | D8: 4 | E8: 5 | F8: 6
D12: Подпись
E13: должность, Ф.И.О. исполнителя и его контактный телефон

Sheet раздел XII
B9: ХII. СЕРТИФИКАЦИЯ И КАЧЕСТВО

Sheet XII-1
A1: Таблица XII/1
A2: Сокращенное наименование организации
A4: Отчет о результатах анализа деятельности организации в области качества
A5: (заполняется по разделам в следующей последовательности)
A7: 1 Сведения о наличии и состоянии сертификации СМК (состояние СМК, применяемый массив-фонд документов СМК, использование CМК по стандарту ГОСТ Р ИСО 9001- 2001, незавершенные работы по реализации в полном объеме ГОСТ РВ 15.002, возникшие проблемы, проявляющиеся тенденции, резервы и рычаги улучшения).
A8: 2 Сведения о составе, структуре, статусе (независимость) компетентности, (аккредитация и аттестация), подчиненности и численности подразделений, контролеров, непосредственно занятых работами в области качества (применительно к заместителю генерального директора по качеству, ответственному представителю руководства по СМК, службе качества, отделу технического контроля, лабораториям испытательным, измерительным, химического анализа и неразрушающего контроля, подразделениям надежности, нормоконтроля, внутреннего аудита СМК, стандартизации, метрологического обеспечения, гарантийного и авторского надзора, обращения технической документации и документов в области стандартизации и других, проводящих экспертизу, обследования, контроль, мониторинг, поверки, калибровки, измерения, проверки, аудиты, анализ и оценку соответствия в области качества).
A9: 3 Мероприятия по вовлечению персонала организации в работу по повышению ответственности, компетентности и качества выпускаемой продукции (подготовка, переподготовка, аттестация, расстановка, определение целей, функций и задач, распределение ответственности и полномочий, отлаженность взаимодействия, достигнутые результаты участия высшего руководства в анализе состояния СМК, вознаграждение, и поощрение).
A10: 4 Сведения по качеству закупаемых и поставляемых изделий с детализацией информации о ПКИ, поставляемых по кооперации организации интегрированной структуры (применение и состояние реализации программ качества и надежности, планов технологической подготовки производства и постановки продукции на производство. Общее состояние качества, ресурсы эффективности, паспортизации и аттестации производств, технологических систем, систем, обеспечивающих их функционирование, технологических процессов, рабочих мест, краткий обобщающий анализ качества продукции, технической документации с раскрытием сведений по рекламациям, отказам, возвратам, браку, отступлениям от технической документации, выпущенным и проведенным извещениям об изменении, приостановкам производства и приемки, о существенной корректировке технической документации, выпуску и состоянию реализации бюллетеней на доработку, корректировку. Возникшие проблемы, проявляющиеся негативные тенденции, резервы и рычаги улучшения. Отлаженность и состояние учета, отчетности и анализа).
A11: 5 Наличие и состояние выполнения программ реструктуризации и перевооружения (технического переоснащения) организации (в части касающейся СМК и области качества).
A12: 6 Основные результаты инспекционных проверок органами по сертификации и аккредитации, госконтроля продукции и производств, внешних и внутренних аудитов СМК (наличие договоров инспекционных проверок, программ и планов аудита СМК, состояние их реализации, характерные несоответствия и их причины, возникающие проблемы, проявляющиеся негативные тенденции, резервы и рычаги улучшения, отлаженность учета, отчетности и анализа, состояние дел по устранению несоответствий и исключению причин их вызывающих).
A13: 7 Планируемые работы по совершенствованию деятельности в области качества (наименования документируемых планов, основные мероприятия и сроки их выполнения).
A14: 8 Выводы и предложения.
... A22: должность, Ф.И.О. исполнителя и его контактный телефон

Sheet XII-2
K1: Таблица XII/2
A2: Сокращенное название организации
A4: Сведения по качеству документации за отчетный год
A5: (подлежит согласованию с ПЗ в части продукции военного назначения)
A7: №п/п | B7: Наименование, обозначение продукции | C7: Вид технической документации (с указанием литеры) | D7: Количество выпущенных извещений об изменениях по технической документации (шт) | K7: Затраты на устранение дефектов изделия в процессе производств (н.час/т.руб.)
D8: на этапе производства (причины и код изменения) | H8: на этапе эксплуатации (причины и код изменения)
D10: устранение ошибок | E10: усовершенствование конструкции | F10: усовершенствование технологии | G10: по результатам испытаний | H10: устранение ошибок | I10: усовершенствование конструкции | J10: прочие
A11: 1 | B11: 2 | C11: 3 | D11: 4 | E11: 5 | F11: 6 | G11: 7 | H11: 8 | I11: 9 | J11: 10 | K11: 11
A12: Раздел 1. Продукция военного назначения
C13: КД, литера О
C14: ТД, литера О1
C15: РД, литера А
A17: Раздел 2. Продукция гражданского назначения
E22: Подпись
F23: должность, Ф.И.О. исполнителя и его контактный телефон

Sheet XII-3
M1: Таблица XII/3
B2: Сокращенное наименование организации
A4: Сведения о собственных затратах на погашение рекламаций за отчетный год
A5: (подлежат согласованию с ПЗ в части продукции военного назначения)
A7: № п/п | B7: Наименование продукции | C7: Номер и дата государственного контракта | D7: Кол-во | E7: Реквизиты рекламаци-онного акта (номер, дата, кем оформлен) | F7: Реквизиты акта удовлетворе-ния рекламации | G7: Причины неработоспособности изделия | K7: Затраты по рекламациям, тыс.руб. | L7: Штрафные санкции
G8: производст- венные дефекты | H8: конструкторские дефекты | I8: отказы ПКИ | J8: вина эксплуа-тации | L8: предъ-явленные, тыс.руб. | M8: оплаченные, тыс.руб.
A10: 1 | B10: 2 | C10: 3 | D10: 4 | E10: 5 | F10: 6 | G10: 7 | H10: 8 | I10: 9 | J10: 10 | K10: 11 | L10: 12 | M10: 13
A11: 1. Продукция военного назначения
A12: 1 | B12: 2 | C12: 22 | D12: 4 | G12: 5 | H12: 6 | I12: 7 | J12: 8 | L12: 9 | M12: 10
A16: 2. Продукция гражданского и двойного назначения
H20: Подпись
I21: должность, Ф.И.О. исполнителя и его контактный телефон

Sheet раздел XIII
A9: ХIII. УРОВЕНЬ АВТОМАТИЗАЦИИ

Sheet XIII-1
H1: Таблица XIII/1
A2: Сокращенное название организации
A4: Внешние каналы связи
A6: 1.1. Глобальная сеть (интернет)
A7: № п/п канала интернет | B7: Способ подключения (оптика, витая пара, модем и т.д.) | C7: Провайдер (поставщик услуг) | D7: Пропускная способность канала (Мбит/сек) | E7: Оборудование, подключенное к каналам интернет
E8: количество серверов | F8: количество рабочих станций
A9: 1 | B9: 2 | C9: 3 | D9: 4 | E9: 5 | F9: 6
A14: 1.2 Внешние каналы связи (выделенные линии)
A15: № п/п | B15: Способ подключения (оптика, витая пара, модем и т.д.) | C15: Имя канала | D15: Пропускная способность канала (Мбит/сек) | E15: Начальная точка (адрес места нахождения) | F15: Конечная точка (адрес места нахождения) | G15: Цель использования | H15: Гриф передаваемой информации
A16: 1 | B16: 2 | C16: 3 | D16: 4 | E16: 5 | F16: 6 | G16: 7 | H16: 8
E20: Подпись
F21: должность, Ф.И.О. исполнителя и его контактный телефон

Sheet XIII-2
I1: Таблица XIII/2
A2: Сокращенное название организации
A4: Локально-вычислительная сеть
A6: № п/п сети | B6: № п/п сегмента сети | C6: Пропускная способность (Мбит/сек) | D6: Количество серверов | E6: Количество сетевых хранилищ | F6: Количество рабочих станций | G6: Количество сетевых периферийных устройств | H6: Гриф обрабатываемой информации | I6: Наличие сертификата (да/нет)
A7: 1 | B7: 2 | C7: 3 | D7: 4 | E7: 5 | F7: 6 | G7: 7 | H7: 8 | I7: 9
F11: Подпись
G12: должность, Ф.И.О. исполнителя и его контактный телефон

Sheet XIII-3
J1: Таблица XIII/3
A2: Сокращенное название организации
A4: Серверное оборудование (серверы и хранилища данных)
A6: № п/п | B6: Производитель (вендор) | C6: Модель | D6: Сетевое имя | E6: Основные аппаратные характеристики (количество процессоров, частота, оперативная память, дисковое пространство) | F6: Операционная система | G6: Разрядность ОС (32/64) | H6: Язык интерфейса (рус/англ.) | I6: Прикладное ПО и СУБД | J6: Количество подключенных АРМ
A7: 1 | B7: 2 | C7: 3 | D7: 4 | E7: 5 | F7: 6 | G7: 7 | H7: 8 | I7: 9 | J7: 10
F11: Подпись
G12: должность, Ф.И.О. исполнителя и его контактный телефон

Sheet XIII-4
I1: Таблица XIII/4
A2: Сокращенное название организации
A4: Персональные компьютеры и терминальные рабочие станции
A6: № п/п | B6: Основные аппаратные характеристики (для ПК – процессор, объем оперативной памяти, для ТРС – имя сервера из формы XIII/3) | C6: Тип (ПК, ноутбук, ТРС) | D6: Распределение ПК по структурным подразделениям (в шт.)
D7: управление | E7: бухгалтерия | F7: конструкторские подразделения | G7: технологические подразделения | H7: цеховые службы | I7: прочие службы
A8: 1 | B8: 2 | C8: 3 | D8: 4 | E8: 5 | F8: 6 | G8: 7 | H8: 8 | I8: 9
F13: Подпись
G14: должность, Ф.И.О. исполнителя и его контактный телефон

Sheet XIII-5
K1: Таблица XIII/5
A2: Сокращенное название организации
A4: Периферийное оборудование
A6: № п/п | B6: Тип (принтер, сканер, МФУ и т.п.) | C6: Производитель (вендор) | D6: Модель | E6: Основные аппаратные характеристики (тип печати, формат, качество dpi) | F6: Распределение периферийного оборудования по структурным подразделениям (в шт.)
F7: управление | G7: бухгалтерия | H7: конструкто- рские подразделения | I7: технологиче- ские подразделения | J7: цеховые службы | K7: прочие службы
A8: 1 | B8: 2 | C8: 3 | D8: 4 | E8: 5 | F8: 6 | G8: 7 | H8: 8 | I8: 9 | J8: 10 | K8: 11
G13: Подпись
H14: должность, Ф.И.О. исполнителя и его контактный телефон

Sheet XIII-6
J1: Таблица XIII/6
A2: Сокращенное название организации
A4: Операционные системы, СУБД, АСУ и прикладные программы
A6: № п/п | B6: Тип (ОС, СУБД, АСУ и т.д.) | C6: Наименование | D6: Разработчик | E6: Место установки (имя сервера из формы XIII/3) | F6: Область применения (выполняемые задачи) | G6: Сведения о лицензировании
G7: лицензионное (количество лицензий, шт.) | I7: собственная разработка (указать язык программирования)
G8: в наличии | H8: необходимо
A9: 1 | B9: 2 | C9: 3 | D9: 4 | E9: 5 | F9: 6 | G9: 7 | H9: 8 | I9: 9
G14: Подпись
H15: должность, Ф.И.О. исполнителя и его контактный телефон

Sheet XIII-7
J1: Таблица XIII/7
B2: Сокращенное название организации
B4: Создание и внедрение автоматизированных систем
A6: № п/п | B6: Название | C6: Назначение и описание | D6: Планируемая дата ввода в эксплуатацию | E6: Этап создания | F6: Разработчик | G6: Программное обеспечение | H6: Количество АРМ | I6: Сопряжение с иными АС | J6: Степень секретности
A7: 1 | B7: 2 | C7: 3 | D7: 4 | E7: 5 | F7: 6 | G7: 7 | H7: 8 | I7: 9 | J7: 10
F12: Подпись
G13: должность, Ф.И.О. исполнителя и его контактный телефон

Sheet Раздел XIV
A9: XIV. ПОТРЕБЛЕНИЕ РЕСУРСОВ, ЭНЕРГОСБЕРЕЖЕНИЕ И ОХРАНА ОКРУЖАЮЩЕЙ СРЕДЫ

Sheet XIV-1
F1: Таблица XIV/1
A2: Сокращенное название организации
A4: Сведения о расходах (размерах оплаты) ресурсов по видам
F6: тыс.руб. с учетом НДС
A7: Код строки | B7: Наименование ресурса по видам | C7: Потреблено | D7: Начислено | E7: Оплачено | F7: Задолженность (переплата)
A8: 1 | B8: 2 | C8: 3 | D8: 4 | E8: 5 | F8: 6
A9: 10 | B9: Горячее водоснабжение
A10: 20 | B10: Холодное водоснабжение
A11: 30 | B11: Канализация
A12: 40 | B12: Водопотребление
A13: 50 | B13: Водоотведение
A14: 60 | B14: Электроснабжение
A15: 70 | B15: Газоснабжение
A16: 80 | B16: Отопление
A17: 90 | B17: Мазут, котельно-печное топливо
A18: 100 | B18: Дизельное топливо
A19: 110 | B19: Бензин
A20: 120 | B20: Керосин
... A26: 180 | B26: Итого по всем ресурсам:
C28: Подпись
D29: должность, Ф.И.О. исполнителя и его контактный телефон

Sheet XIV-2
D1: Таблица XIV/2
A2: Сокращенное название организации
B4: Сведения о потреблении электроэнергии на технологические нужды
D6: (тыс. кВт час)
A7: Код строки | B7: Наименование параметра | C7: Отчетный год | D7: Предыдущий отчетному год
A8: 1 | B8: 2 | C8: 3 | D8: 4
A9: 100 | B9: Общее потребление электроэнергии на технологические нужды всего, в том числе:
A10: 101 | B10: Металлургическое производство
A11: 102 | B11: Производство оптических материалов и оптических сред
A12: 103 | B12: Литейное производство
A13: 104 | B13: Кузнечно-прессовое производство
A14: 105 | B14: Механообрабатывающее производство
A15: 106 | B15: Изготовление оптических деталей
A16: 107 | B16: Быстрое прототипирование и изготовление деталей на основе аддитивных технологий
A17: 108 | B17: Химическое производство
A18: 109 | B18: Гальванохимическое производство
A19: 110 | B19: Термическое и химико-термическое производство
A20: 111 | B20: Нанесение защитных покрытий
... A44: 400 | B44: Непроизводственные (хозяйственные) нужды
B46: Подпись
C47: должность, Ф.И.О. исполнителя и его контактный телефон

Sheet XIV-3
D1: Таблица XIV/3
A2: Сокращенное название организации
A4: Водопотребление и водоотведение за отчетный год
D5: Тыс. м³/год
A6: Код строки | B6: Наименование показателей | C6: Отчетный год | D6: Предыдущий год
A8: 1 | B8: 2 | C8: 3 | D8: 4
A9: 100 | B9: Забрано воды, всего, в том числе:
A10: 101 | B10: из поверхностных вод (водоканалы, водоемы, другие водные объекты)
A11: 102 | B11: из подземных вод (артезианские скважины)
A12: 103 | B12: из городского водопровода
A13: 104 | B13: из технического водопровода
A14: 105 | B14: из систем оборотного водоснабжения
A15: 106 | B15: из систем повторного водоснабжения
A16: 107 | B16: получено от поставщиков
A17: 200 | B17: Использовано воды, всего, в том числе:
A18: 201 | B18: на производственные нужды
A19: 202 | B19: на питьевые и хозяйственно-бытовые нужды
A20: 203 | B20: передано другим юридическим и физическим лицам
... A32: 700 | B32: Объем воды, повторно используемой организацией
B34: Подпись
C35: должность, Ф.И.О. исполнителя и его контактный телефон

Sheet XIV-4
I1: Таблица XIV/4
B2: Сокращенное название организации
B4: Сведения о системе инженерно-технических сетей, коммуникаций и инфраструктуры зданий и сооружений, производственных площадок
A6: № п/п | B6: Наименование объекта | C6: Дата ввода в эксплуатацию | D6: Тип | E6: Технические характеристики системы инженерно-технических сетей, коммуникаций | J6: Технические характеристики системы инженерно-технических сетей, коммуникаций (продолжение) | N6: Объем потерь (тепла, давления, температуры, мощности и т.п.) | O6: Техническое состояние | P6: Количество аварий за год, единиц | Q6: Год последнего капитального ремонта объекта | R6: Сумма фактических затрат на содержание и ремонт объекта за отчетный год, тыс.руб. | S6: Примечание
E7: протяженность, м | F7: диаметр, м | G7: рабочее давление, Мпа | H7: рабочая температура, С | I7: мощность, кВт | J7: напряжение, кВ | K7: частота, Гц | L7: тепловая мощность, Гкал | M7: расход, м3/час
A8: 1 | B8: 2 | C8: 3 | D8: 4 | E8: 5 | F8: 6 | G8: 7 | H8: 8 | I8: 9 | J8: 10 | K8: 11 | L8: 12 | M8: 13 | N8: 14 | O8: 15 | P8: 16 | Q8: 17 | R8: 18 | S8: 19
P13: Подпись
Q14: должность, Ф.И.О. исполнителя и его контактный телефон

Sheet XIV-5
K1: Таблица XIV/5
B2: Сокращенное название организации
B4: Мероприятия по энергосбережению и охране окружающей среды
A6: № п/п | B6: Наименование мероприятия | C6: Плановый срок исполнения, дата | D6: Фактический срок исполнения, дата | E6: Планируемый объем затрат по плану мероприятий, всего, тыс.руб. | F6: Планируемый объем затрат с разбивкой по годам действия плана мероприятий, тыс.руб. | L6: Фактический объем затрат в отчетном году, тыс.руб. | M6: Источники финансирования затрат в отчетном году, тыс.руб. | R6: Экономия по плану | T6: Экономия по факту | V6: Срок окупаемости (лет)
F8: в отчетном году | G8: в следующем за отчетным году | H8: на 2 год после отчетного | I8: на 3 год после отчетного | J8: на 4 год после отчетного | K8: на 5 год после отчетного | M8: федераль-ный бюджет | N8: бюджет субъекта РФ | O8: местный бюджет | P8: собственные средства | Q8: заемные средства | R8: в натуральном выражении (тыс. кВтч) | S8: в стоимостном исчислении (тыс. руб.) | T8: в натуральном выражении (тыс. кВтч) | U8: в стоимостном исчислении (тыс. руб.)
A9: 1 | B9: 2 | C9: 3 | D9: 4 | E9: 5 | F9: 6 | G9: 7 | H9: 8 | I9: 9 | J9: 10 | K9: 11 | L9: 12 | M9: 13 | N9: 14 | O9: 15 | P9: 16 | Q9: 17 | R9: 18 | S9: 19 | T9: 20 | U9: 21 | V9: 22
R14: Подпись
S15: должность, Ф.И.О. исполнителя и его контактный телефон
